[
  {
    "id": 1,
    "tags": [
      "无需动画"
    ],
    "confusion": "20%的中国人死于吃错饭是真的吗"
  },
  {
    "id": 2,
    "tags": [
      "无需动画"
    ],
    "confusion": "2022年流传的健康谣言哪些是假的？"
  },
  {
    "id": 3,
    "tags": [
      "无需动画"
    ],
    "confusion": "2023年流行的健康谣言哪些是假的"
  },
  {
    "id": 4,
    "tags": [
      "骨骼肌纤维萎缩与流失过程",
      "肺泡气体交换机制"
    ],
    "confusion": "50岁后体力下降、容易喘，是正常衰老还是肌肉流失？"
  },
  {
    "id": 5,
    "tags": [
      "冠状动脉狭窄程度与血流变化",
      "冠脉支架植入过程"
    ],
    "confusion": "70%血管狭窄到底该不该放支架？"
  },
  {
    "id": 6,
    "tags": [
      "AED除颤仪电击恢复心律过程",
      "心室颤动与正常心律对比"
    ],
    "confusion": "AED是什么？普通人怎么用它救人？"
  },
  {
    "id": 7,
    "tags": [
      "心脏收缩射血过程与射血分数示意",
      "心力衰竭时心腔扩大与泵血功能下降"
    ],
    "confusion": "BNP高、射血分数低但没症状算不算心衰？"
  },
  {
    "id": 8,
    "tags": [
      "HPV病毒感染宫颈细胞过程",
      "宫颈细胞病变分级示意"
    ],
    "confusion": "HPV和TCT检查结果怎么看"
  },
  {
    "id": 9,
    "tags": [
      "OCT光学相干断层扫描血管内壁成像",
      "冠脉造影与OCT成像对比"
    ],
    "confusion": "OCT检查比造影好在哪里"
  },
  {
    "id": 10,
    "tags": [
      "冠状动脉前降支近端严重狭窄",
      "心电图特征性T波改变示意"
    ],
    "confusion": "Wellens综合征是什么"
  },
  {
    "id": 11,
    "tags": [
      "多种药物分别作用于不同靶器官示意"
    ],
    "confusion": "一个人为什么要吃十几种药"
  },
  {
    "id": 12,
    "tags": [
      "药物在体内血药浓度变化曲线"
    ],
    "confusion": "一日三次吃药是不是跟着三餐吃"
  },
  {
    "id": 13,
    "tags": [
      "无需动画"
    ],
    "confusion": "三伏天晒太阳是否更健康，晒太阳的正确方式是什么"
  },
  {
    "id": 14,
    "tags": [
      "阿司匹林抑制血小板聚集机制",
      "动脉粥样硬化斑块破裂与血栓形成"
    ],
    "confusion": "上了年纪是不是都应该吃阿司匹林预防心梗脑梗"
  },
  {
    "id": 15,
    "tags": [
      "下肢动脉闭塞后远端缺血示意",
      "热刺激导致组织需氧量增加与缺血加重"
    ],
    "confusion": "下肢动脉闭塞的人为什么不能泡脚"
  },
  {
    "id": 16,
    "tags": [
      "冠状动脉三支病变示意",
      "动脉粥样硬化斑块形成过程"
    ],
    "confusion": "不到40岁为什么会得严重的三支冠脉病变？"
  },
  {
    "id": 17,
    "tags": [
      "胆囊收缩排空胆汁过程",
      "胆汁淤积与胆固醇结晶形成胆结石"
    ],
    "confusion": "不吃早餐会不会导致胆结石"
  },
  {
    "id": 18,
    "tags": [
      "肝脏内源性合成甘油三酯过程",
      "碳水化合物在肝脏转化为脂肪的代谢通路"
    ],
    "confusion": "不吃油不吃肉为什么甘油三酯还是高"
  },
  {
    "id": 19,
    "tags": [
      "胰岛β细胞分泌胰岛素过程",
      "胰岛素抵抗与β细胞功能衰竭"
    ],
    "confusion": "不吃甜食生活习惯也好为什么还会得糖尿病？"
  },
  {
    "id": 20,
    "tags": [
      "骨骼肌纤维萎缩与流失过程",
      "蛋白质消化吸收与氨基酸代谢通路"
    ],
    "confusion": "不吃肉/蛋白质摄入不足对身体有什么危害？"
  },
  {
    "id": 21,
    "tags": [
      "无需动画"
    ],
    "confusion": "不吃药只靠改变生活方式能改善健康指标吗"
  },
  {
    "id": 22,
    "tags": [
      "肝脏合成与代谢胆固醇过程",
      "低密度脂蛋白在血管壁沉积过程"
    ],
    "confusion": "不吃药有什么办法可以降血脂？"
  },
  {
    "id": 23,
    "tags": [
      "肝脏合成与代谢胆固醇过程"
    ],
    "confusion": "不吃药能不能降低血脂"
  },
  {
    "id": 24,
    "tags": [
      "他汀类药物作用于肝细胞HMG-CoA还原酶",
      "胰岛β细胞分泌胰岛素过程"
    ],
    "confusion": "不同他汀对血糖影响是否不同"
  },
  {
    "id": 25,
    "tags": [
      "人体腹部脏器分区与定位示意"
    ],
    "confusion": "不同位置的肚子痛分别是什么原因"
  },
  {
    "id": 26,
    "tags": [
      "无需动画"
    ],
    "confusion": "不同年龄段体检应该重点关注什么"
  },
  {
    "id": 27,
    "tags": [
      "不同降压药作用靶点示意"
    ],
    "confusion": "不同降压药各有哪些常见副作用"
  },
  {
    "id": 28,
    "tags": [
      "动脉粥样硬化斑块形成过程",
      "血管内皮损伤与炎症反应"
    ],
    "confusion": "不抽烟不喝酒、血脂也不高，血管为什么还会堵？"
  },
  {
    "id": 29,
    "tags": [
      "果糖在肝脏代谢转化为脂肪的通路",
      "血糖升高与胰岛素分泌响应"
    ],
    "confusion": "不甜的水果是不是就不会让人胖/升血糖？"
  },
  {
    "id": 30,
    "tags": [
      "无需动画"
    ],
    "confusion": "专科分太细会不会漏诊？"
  },
  {
    "id": 31,
    "tags": [
      "无需动画"
    ],
    "confusion": "中医治疗白血病是否有效，该不该信中医"
  },
  {
    "id": 32,
    "tags": [
      "动脉粥样硬化斑块形成过程",
      "冠状动脉与脑动脉血栓形成"
    ],
    "confusion": "中年人如何保护血管预防心梗脑梗"
  },
  {
    "id": 33,
    "tags": [
      "冠状动脉内斑块破裂与血栓形成",
      "动脉粥样硬化早期血管内皮损伤"
    ],
    "confusion": "为什么19岁年轻人也会突发心梗"
  },
  {
    "id": 34,
    "tags": [
      "骨骼微观结构中骨质流失过程",
      "钙在肠道吸收与维生素D的作用"
    ],
    "confusion": "为什么一直在补钙还是骨质疏松？"
  },
  {
    "id": 35,
    "tags": [
      "冠状动脉内斑块破裂与血栓形成",
      "动脉粥样硬化早期血管内皮损伤"
    ],
    "confusion": "为什么不抽烟不喝酒的年轻人也会突然心梗"
  },
  {
    "id": 36,
    "tags": [
      "动脉粥样硬化斑块形成过程"
    ],
    "confusion": "为什么中国心脏病越来越多而欧美越来越少？"
  },
  {
    "id": 37,
    "tags": [
      "胰岛素抵抗与β细胞功能衰竭"
    ],
    "confusion": "为什么中国糖尿病患者这么多"
  },
  {
    "id": 38,
    "tags": [
      "肿瘤细胞从微小病灶发展到晚期的过程"
    ],
    "confusion": "为什么体检正常，几个月后就查出肿瘤晚期"
  },
  {
    "id": 39,
    "tags": [
      "脂肪分解产生酮体与嘌呤代谢增加导致尿酸升高",
      "肾脏排泄尿酸机制"
    ],
    "confusion": "为什么减肥后尿酸反而升高了"
  },
  {
    "id": 40,
    "tags": [
      "下丘脑饥饿信号与瘦素抵抗机制",
      "脂肪细胞萎缩后激素变化"
    ],
    "confusion": "为什么减肥这么难？为什么一控制饮食就饿？"
  },
  {
    "id": 41,
    "tags": [
      "无需动画"
    ],
    "confusion": "为什么医生当面说没事但病历上写的是很高危"
  },
  {
    "id": 42,
    "tags": [
      "深静脉血栓脱落经右心进入肺动脉导致肺栓塞",
      "下肢深静脉血栓形成过程"
    ],
    "confusion": "为什么卧床后突然活动或术后容易发生肺栓塞"
  },
  {
    "id": 43,
    "tags": [
      "胃食管反流刺激气管引起咳嗽反射",
      "气道高反应性与支气管痉挛"
    ],
    "confusion": "为什么只在夜间咳嗽、止咳药无效、CT也查不出原因"
  },
  {
    "id": 44,
    "tags": [
      "内脏脂肪与皮下脂肪分布示意",
      "基础代谢率与能量消耗机制"
    ],
    "confusion": "为什么吃得很少肚子还是减不下去"
  },
  {
    "id": 45,
    "tags": [
      "肝脏内源性合成胆固醇过程",
      "低密度脂蛋白在血管壁沉积过程"
    ],
    "confusion": "为什么吃得清淡血脂反而高"
  },
  {
    "id": 46,
    "tags": [
      "胰岛素大量分泌导致血糖骤降引发饥饿感",
      "血糖升高与胰岛素分泌响应"
    ],
    "confusion": "为什么吃得越撑反而饿得越快？"
  },
  {
    "id": 47,
    "tags": [
      "胰岛素大量分泌导致血糖骤降引发饥饿感",
      "血糖升高与胰岛素分泌响应"
    ],
    "confusion": "为什么吃得越饱反而饿得越快"
  },
  {
    "id": 48,
    "tags": [
      "幽门螺杆菌定植胃黏膜过程"
    ],
    "confusion": "为什么常规体检不推荐查幽门螺杆菌？"
  },
  {
    "id": 49,
    "tags": [
      "肿瘤细胞从微小病灶发展到晚期的过程"
    ],
    "confusion": "为什么年年体检还会突然生病？"
  },
  {
    "id": 50,
    "tags": [
      "肾小球滤过功能逐步丧失过程",
      "肾单位损伤与纤维化"
    ],
    "confusion": "为什么年轻人得尿毒症越来越多？"
  },
  {
    "id": 51,
    "tags": [
      "动脉粥样硬化斑块形成过程",
      "冠状动脉狭窄程度与血流变化"
    ],
    "confusion": "为什么心脏病患者越来越多"
  },
  {
    "id": 52,
    "tags": [
      "心房颤动时心房电信号紊乱",
      "射频消融术消除异常电信号过程",
      "心房纤维化与电重构"
    ],
    "confusion": "为什么房颤早期该做消融而拖成持续性反而不建议了"
  },
  {
    "id": 53,
    "tags": [
      "大脑多巴胺奖赏回路与糖成瘾机制"
    ],
    "confusion": "为什么控制不住想吃甜食？"
  },
  {
    "id": 54,
    "tags": [
      "冠脉支架内再狭窄过程",
      "抗血小板药物抑制血栓形成机制"
    ],
    "confusion": "为什么支架术后不好好吃药血管会反复堵塞"
  },
  {
    "id": 55,
    "tags": [
      "冠脉支架内新生内膜增生导致再狭窄",
      "冠脉支架植入过程"
    ],
    "confusion": "为什么放完支架血管还是会再堵"
  },
  {
    "id": 56,
    "tags": [
      "动脉粥样硬化斑块形成过程",
      "健康血管内皮与受损血管内皮对比"
    ],
    "confusion": "为什么有人79岁血管不堵而40岁就堵了"
  },
  {
    "id": 57,
    "tags": [
      "基础代谢率差异与能量消耗机制",
      "脂肪细胞储存与分解脂肪过程"
    ],
    "confusion": "为什么有人怎么吃都不胖，有人喝水都胖？"
  },
  {
    "id": 58,
    "tags": [
      "冠脉支架内新生内膜增生导致再狭窄",
      "抗血小板药物抑制血栓形成机制"
    ],
    "confusion": "为什么有人放完支架几个月又堵了？"
  },
  {
    "id": 59,
    "tags": [
      "剧烈运动时心脏负荷增加与冠脉供血不足",
      "运动中心肌耗氧量变化"
    ],
    "confusion": "为什么有人经常锻炼反而身体出问题甚至猝死"
  },
  {
    "id": 60,
    "tags": [
      "自主神经系统（交感与副交感）调节示意"
    ],
    "confusion": "为什么植物神经紊乱吃药好不了"
  },
  {
    "id": 61,
    "tags": [
      "动脉粥样硬化斑块破裂与血栓形成",
      "血压测量时血管状态与日常血管状态差异"
    ],
    "confusion": "为什么每次量血压都正常却还是出现了心梗脑梗"
  },
  {
    "id": 62,
    "tags": [
      "冠状动脉狭窄程度与血流变化",
      "侧支循环代偿供血示意"
    ],
    "confusion": "为什么没有症状医生却说病情很严重？"
  },
  {
    "id": 63,
    "tags": [
      "动脉粥样硬化斑块形成过程"
    ],
    "confusion": "为什么现在心脏病人越来越多"
  },
  {
    "id": 64,
    "tags": [
      "肾小球滤过功能逐步丧失过程",
      "肾单位损伤与纤维化"
    ],
    "confusion": "为什么现在肾衰竭透析的人越来越多？"
  },
  {
    "id": 65,
    "tags": [
      "心室颤动与正常心律对比",
      "动脉粥样硬化斑块破裂与血栓形成"
    ],
    "confusion": "为什么看似健康的人会突然猝死"
  },
  {
    "id": 66,
    "tags": [
      "肾小球滤过功能逐步丧失过程",
      "肾单位损伤与纤维化"
    ],
    "confusion": "为什么肾衰竭需要透析的人越来越多"
  },
  {
    "id": 67,
    "tags": [
      "肾小球滤过功能逐步丧失过程",
      "肾单位损伤与纤维化",
      "血肌酐与肾小球滤过率的关系"
    ],
    "confusion": "为什么肾衰透析的人越来越多、肌酐为什么一年比一年高"
  },
  {
    "id": 68,
    "tags": [
      "肥胖导致外周血管阻力增加机制",
      "舒张压与血管弹性的关系"
    ],
    "confusion": "为什么胖的人容易低压（舒张压）升高"
  },
  {
    "id": 69,
    "tags": [
      "胰腺解剖位置与周围重要结构",
      "胰腺癌侵犯周围血管与神经"
    ],
    "confusion": "为什么胰腺癌被称为癌中之王"
  },
  {
    "id": 70,
    "tags": [
      "动脉粥样硬化斑块快速进展过程",
      "斑块破裂与血栓形成导致急性闭塞"
    ],
    "confusion": "为什么血管会在短短一年内迅速堵塞"
  },
  {
    "id": 71,
    "tags": [
      "侧支循环代偿供血示意",
      "冠状动脉狭窄程度与血流变化"
    ],
    "confusion": "为什么血管堵得很严重却完全没有症状？"
  },
  {
    "id": 72,
    "tags": [
      "胰岛素抵抗与β细胞功能衰竭"
    ],
    "confusion": "为什么越来越多年轻人得糖尿病"
  },
  {
    "id": 73,
    "tags": [
      "动脉粥样硬化斑块形成过程",
      "冠状动脉与脑动脉血栓形成"
    ],
    "confusion": "为什么身边心梗脑梗的人越来越多？"
  },
  {
    "id": 74,
    "tags": [
      "血压在一天内的波动规律曲线",
      "动脉血管壁弹性与压力变化"
    ],
    "confusion": "为什么连续量血压每次结果都不一样"
  },
  {
    "id": 75,
    "tags": [
      "主动脉壁三层结构撕裂过程",
      "主动脉夹层血液进入假腔示意"
    ],
    "confusion": "主动脉夹层是什么、有多危险？"
  },
  {
    "id": 76,
    "tags": [
      "碳水化合物消化吸收与血糖响应"
    ],
    "confusion": "主食到底应该多吃还是少吃"
  },
  {
    "id": 77,
    "tags": [
      "无需动画"
    ],
    "confusion": "久不运动刚开始跑步为什么会肚子痛"
  },
  {
    "id": 78,
    "tags": [
      "乙肝病毒感染肝细胞复制过程",
      "肝炎-肝硬化-肝癌三步演变过程"
    ],
    "confusion": "乙肝为什么容易发展到肝癌才被发现？"
  },
  {
    "id": 79,
    "tags": [
      "乙肝病毒抗原抗体免疫反应示意"
    ],
    "confusion": "乙肝五项怎么看"
  },
  {
    "id": 80,
    "tags": [
      "乙肝病毒感染肝细胞复制过程",
      "乙肝疫苗激活免疫系统产生抗体"
    ],
    "confusion": "乙肝是否可防可治，乙肝携带者是否需要被歧视"
  },
  {
    "id": 81,
    "tags": [
      "乙肝病毒抗原抗体免疫反应示意"
    ],
    "confusion": "乙肝表面抗体阳性是感染了吗"
  },
  {
    "id": 82,
    "tags": [
      "免疫细胞识别与攻击肿瘤细胞过程",
      "肿瘤细胞免疫逃逸机制"
    ],
    "confusion": "人为什么会得肿瘤、跟免疫力有没有关系"
  },
  {
    "id": 83,
    "tags": [
      "人体内脏器官位置全景解剖示意"
    ],
    "confusion": "人体内脏各在什么位置"
  },
  {
    "id": 84,
    "tags": [
      "心脏四腔结构与瓣膜开闭过程",
      "心脏血液流动方向示意"
    ],
    "confusion": "人的心脏内部结构到底是什么样的"
  },
  {
    "id": 85,
    "tags": [
      "细胞端粒缩短与细胞衰老过程"
    ],
    "confusion": "人的衰老是匀速的还是断崖式的"
  },
  {
    "id": 86,
    "tags": [
      "动脉血管壁增厚硬化过程",
      "肾素-血管紧张素-醛固酮系统调节血压"
    ],
    "confusion": "人的身体是怎么一步步走向高血压的"
  },
  {
    "id": 87,
    "tags": [
      "冠脉造影导管从桡动脉进入冠状动脉过程"
    ],
    "confusion": "什么人需要做冠脉造影检查"
  },
  {
    "id": 88,
    "tags": [
      "他汀类药物作用于肝细胞HMG-CoA还原酶",
      "低密度脂蛋白在血管壁沉积过程"
    ],
    "confusion": "什么情况下吃他汀才真正获益"
  },
  {
    "id": 89,
    "tags": [
      "冠状动脉狭窄程度与血流变化",
      "冠脉支架植入过程"
    ],
    "confusion": "什么情况下需要放心脏支架？没症状要不要放？"
  },
  {
    "id": 90,
    "tags": [
      "心脏传导系统示意",
      "心脏起搏器植入与电信号调节"
    ],
    "confusion": "什么情况下需要装心脏起搏器"
  },
  {
    "id": 91,
    "tags": [
      "无需动画"
    ],
    "confusion": "什么情况的发烧需要去医院？"
  },
  {
    "id": 92,
    "tags": [
      "冠脉支架植入过程",
      "冠脉搭桥手术旁路血管连接示意"
    ],
    "confusion": "什么情况该放支架，什么情况该搭桥？"
  },
  {
    "id": 93,
    "tags": [
      "冠脉造影导管从桡动脉进入冠状动脉过程"
    ],
    "confusion": "什么情况需要做心脏造影？"
  },
  {
    "id": 94,
    "tags": [
      "动脉血管壁承受压力与血压数值关系"
    ],
    "confusion": "什么才是理想的血压值"
  },
  {
    "id": 95,
    "tags": [
      "AED除颤仪电击恢复心律过程",
      "心室颤动与正常心律对比"
    ],
    "confusion": "什么是AED？为什么运动场所必须配备？"
  },
  {
    "id": 96,
    "tags": [
      "免疫细胞（T细胞、B细胞、巨噬细胞）协同作战"
    ],
    "confusion": "什么是免疫力"
  },
  {
    "id": 97,
    "tags": [
      "免疫细胞（T细胞、B细胞、巨噬细胞）协同作战"
    ],
    "confusion": "什么是免疫力？不生病就代表免疫力强吗？"
  },
  {
    "id": 98,
    "tags": [
      "低密度脂蛋白受体基因突变导致胆固醇无法被肝脏回收",
      "低密度脂蛋白在血管壁沉积过程"
    ],
    "confusion": "什么是家族性高胆固醇血症？怎么判断自己有没有？"
  },
  {
    "id": 99,
    "tags": [
      "微循环毛细血管网络物质交换示意",
      "微循环障碍导致组织缺氧"
    ],
    "confusion": "什么是微循环，微循环障碍有什么危害"
  },
  {
    "id": 100,
    "tags": [
      "自主神经系统（交感与副交感）调节示意",
      "惊恐发作时交感神经过度激活"
    ],
    "confusion": "什么是惊恐发作"
  },
  {
    "id": 101,
    "tags": [
      "高温下人体体温调节中枢失控过程"
    ],
    "confusion": "什么是热射病？高温天气怎么防止被热死？"
  },
  {
    "id": 102,
    "tags": [
      "肾素-血管紧张素-醛固酮系统调节血压",
      "肾上腺或肾动脉病变导致继发性高血压"
    ],
    "confusion": "什么是继发性高血压，能根治吗"
  },
  {
    "id": 103,
    "tags": [
      "肾上腺皮质分泌醛固酮过程",
      "醛固酮促进肾脏重吸收钠和水导致血压升高"
    ],
    "confusion": "什么是醛固酮增多症？"
  },
  {
    "id": 104,
    "tags": [
      "无需动画"
    ],
    "confusion": "什么样的基础病才算新冠重症高危？高血压算吗？"
  },
  {
    "id": 105,
    "tags": [
      "心脏传导系统示意",
      "心律失常类型对比示意"
    ],
    "confusion": "什么样的心慌需要去医院"
  },
  {
    "id": 106,
    "tags": [
      "冠状动脉狭窄导致心肌缺血过程",
      "心绞痛疼痛放射区域体表示意"
    ],
    "confusion": "什么样的胸痛才是心绞痛？心绞痛有哪些特征？"
  },
  {
    "id": 107,
    "tags": [
      "动脉血管壁承受压力与血压数值关系"
    ],
    "confusion": "什么样的血压算健康/完美？"
  },
  {
    "id": 108,
    "tags": [
      "无需动画"
    ],
    "confusion": "什么样的运动才算有效运动"
  },
  {
    "id": 109,
    "tags": [
      "无需动画"
    ],
    "confusion": "什么运动最有利于降血压"
  },
  {
    "id": 110,
    "tags": [
      "免疫细胞（T细胞、B细胞、巨噬细胞）协同作战"
    ],
    "confusion": "从不发烧和经常发烧，哪个说明免疫力更差？"
  },
  {
    "id": 111,
    "tags": [
      "免疫细胞（T细胞、B细胞、巨噬细胞）协同作战"
    ],
    "confusion": "从不发烧和经常发烧，谁的免疫力更差"
  },
  {
    "id": 112,
    "tags": [
      "他汀类药物作用于肝细胞HMG-CoA还原酶",
      "肝脏药物代谢过程"
    ],
    "confusion": "他汀会不会引起糖尿病或伤肝伤肾"
  },
  {
    "id": 113,
    "tags": [
      "他汀类药物作用于肝细胞HMG-CoA还原酶",
      "胰岛β细胞分泌胰岛素过程"
    ],
    "confusion": "他汀到底会不会引起糖尿病该不该继续吃"
  },
  {
    "id": 114,
    "tags": [
      "他汀类药物作用于肝细胞HMG-CoA还原酶",
      "肝脏药物代谢过程"
    ],
    "confusion": "他汀到底伤不伤肝"
  },
  {
    "id": 115,
    "tags": [
      "他汀类药物作用于肝细胞HMG-CoA还原酶",
      "药物在体内血药浓度变化曲线"
    ],
    "confusion": "他汀是否需要晚上吃？"
  },
  {
    "id": 116,
    "tags": [
      "他汀类药物作用于肝细胞HMG-CoA还原酶"
    ],
    "confusion": "他汀有没有副作用"
  },
  {
    "id": 117,
    "tags": [
      "他汀类药物作用于肝细胞HMG-CoA还原酶",
      "药物在体内血药浓度变化曲线"
    ],
    "confusion": "他汀类药物什么时间吃最好"
  },
  {
    "id": 118,
    "tags": [
      "他汀类药物作用于肝细胞HMG-CoA还原酶"
    ],
    "confusion": "他汀类药物怎么正确使用？"
  },
  {
    "id": 119,
    "tags": [
      "脂肪肝肝细胞内脂滴堆积示意",
      "他汀类药物作用于肝细胞HMG-CoA还原酶"
    ],
    "confusion": "他汀能不能用来治疗脂肪肝"
  },
  {
    "id": 120,
    "tags": [
      "冠状动脉狭窄导致心肌缺血过程",
      "侧支循环代偿供血示意"
    ],
    "confusion": "休息时没症状是不是就说明心脏没问题"
  },
  {
    "id": 121,
    "tags": [
      "冠状动脉狭窄导致心肌缺血过程"
    ],
    "confusion": "休息时胸闷活动后缓解是心肌缺血吗"
  },
  {
    "id": 122,
    "tags": [
      "下丘脑饥饿信号与瘦素抵抗机制"
    ],
    "confusion": "传统节食加运动减肥为什么难坚持"
  },
  {
    "id": 123,
    "tags": [
      "舒张压与血管弹性的关系",
      "外周血管阻力与舒张压升高机制"
    ],
    "confusion": "低压高为什么吃药也降不下来"
  },
  {
    "id": 124,
    "tags": [
      "舒张压升高导致心脏负荷增加",
      "动脉粥样硬化斑块破裂与血栓形成"
    ],
    "confusion": "低压高会导致心梗猝死，是否可以不吃药顺其自然"
  },
  {
    "id": 125,
    "tags": [
      "舒张压与血管弹性的关系",
      "外周血管阻力与舒张压升高机制"
    ],
    "confusion": "低压高吃药也降不下来怎么办？"
  },
  {
    "id": 126,
    "tags": [
      "舒张压与血管弹性的关系",
      "外周血管阻力与舒张压升高机制"
    ],
    "confusion": "低压高吃药控制不住怎么办"
  },
  {
    "id": 127,
    "tags": [
      "舒张压与血管弹性的关系",
      "外周血管阻力与舒张压升高机制"
    ],
    "confusion": "低压（舒张压）偏高是怎么回事，有什么危害"
  },
  {
    "id": 128,
    "tags": [
      "舒张压与血管弹性的关系"
    ],
    "confusion": "低压（舒张压）只是稍微偏高需要吃降压药吗"
  },
  {
    "id": 129,
    "tags": [
      "动脉粥样硬化斑块内部结构（低回声与钙化）",
      "不稳定斑块破裂与血栓形成"
    ],
    "confusion": "低回声斑块和钙化斑块哪个更危险"
  },
  {
    "id": 130,
    "tags": [
      "动脉粥样硬化斑块内部结构（低回声与钙化）"
    ],
    "confusion": "低回声斑块需要紧张吗"
  },
  {
    "id": 131,
    "tags": [
      "低密度脂蛋白在血管壁沉积过程"
    ],
    "confusion": "低密度胆固醇在3.4到4.9之间需不需要吃他汀"
  },
  {
    "id": 132,
    "tags": [
      "低密度脂蛋白在血管壁沉积过程",
      "动脉粥样硬化斑块形成过程"
    ],
    "confusion": "低密度胆固醇差一点点真的影响很大吗"
  },
  {
    "id": 133,
    "tags": [
      "低密度脂蛋白在血管壁沉积过程",
      "动脉粥样硬化斑块形成过程"
    ],
    "confusion": "低密度胆固醇真的与心脑血管疾病无关吗"
  },
  {
    "id": 134,
    "tags": [
      "低密度脂蛋白在血管壁沉积过程"
    ],
    "confusion": "低密度脂蛋白/胆固醇天然很低是好事还是坏事？"
  },
  {
    "id": 135,
    "tags": [
      "低密度脂蛋白在血管壁沉积过程",
      "冠状动脉狭窄导致心肌缺血过程"
    ],
    "confusion": "低密度脂蛋白很高会有什么后果，运动胸痛是不是心绞痛"
  },
  {
    "id": 136,
    "tags": [
      "动脉血管壁承受压力与血压数值关系"
    ],
    "confusion": "低血压是病吗？需要吃药治疗吗？"
  },
  {
    "id": 137,
    "tags": [
      "胰岛β细胞分泌胰岛素过程",
      "胰岛素早期过度分泌导致反应性低血糖"
    ],
    "confusion": "低血糖为什么反而是糖尿病早期信号？"
  },
  {
    "id": 138,
    "tags": [
      "低血糖时大脑神经元能量不足",
      "血糖骤降引发交感神经应激反应"
    ],
    "confusion": "低血糖发作有多严重，吃块糖就没事了吗"
  },
  {
    "id": 139,
    "tags": [
      "无需动画"
    ],
    "confusion": "低钠盐、无碘盐、富硒盐等各种盐该怎么选"
  },
  {
    "id": 140,
    "tags": [
      "无需动画"
    ],
    "confusion": "低钠饮食只是少放盐就行了吗？哪些食物隐藏钠含量高？"
  },
  {
    "id": 141,
    "tags": [
      "无需动画"
    ],
    "confusion": "体检中哪些关键项目容易被忽略？"
  },
  {
    "id": 142,
    "tags": [
      "心电传导系统示意",
      "心电图波形与心脏电活动对应关系"
    ],
    "confusion": "体检做心电图到底有没有用"
  },
  {
    "id": 143,
    "tags": [
      "动脉粥样硬化斑块形成过程",
      "动脉硬化导致血管弹性下降"
    ],
    "confusion": "体检发现动脉硬化会不会导致心梗脑梗？"
  },
  {
    "id": 144,
    "tags": [
      "动脉粥样硬化斑块形成过程"
    ],
    "confusion": "体检发现动脉硬化等问题需不需要治疗"
  },
  {
    "id": 145,
    "tags": [
      "动脉粥样硬化斑块内部结构（低回声与钙化）",
      "动脉粥样硬化斑块形成过程"
    ],
    "confusion": "体检发现血管斑块和动脉硬化是不是血管快堵了、要不要马上吃药"
  },
  {
    "id": 146,
    "tags": [
      "颈动脉斑块位置与大脑供血关系",
      "动脉粥样硬化斑块内部结构（低回声与钙化）"
    ],
    "confusion": "体检发现颈动脉斑块要不要治疗，怎么管"
  },
  {
    "id": 147,
    "tags": [
      "颈动脉斑块位置与大脑供血关系",
      "他汀类药物作用于肝细胞HMG-CoA还原酶",
      "阿司匹林抑制血小板聚集机制"
    ],
    "confusion": "体检发现颈动脉斑块需要吃他汀和阿司匹林吗？"
  },
  {
    "id": 148,
    "tags": [
      "无需动画"
    ],
    "confusion": "体检套餐中哪些项目最没用"
  },
  {
    "id": 149,
    "tags": [
      "无需动画"
    ],
    "confusion": "体检套餐是不是越贵越好？"
  },
  {
    "id": 150,
    "tags": [
      "心电传导系统示意",
      "冠状动脉狭窄导致心肌缺血过程",
      "心电图波形与心脏电活动对应关系"
    ],
    "confusion": "体检心电图能不能筛查出冠心病"
  },
  {
    "id": 1,
    "tags": [
      "无需动画"
    ],
    "confusion": "体检报告上哪些异常不需要过度治疗"
  },
  {
    "id": 2,
    "tags": [
      "无需动画"
    ],
    "confusion": "体检报告上哪些异常其实不需要治疗？"
  },
  {
    "id": 3,
    "tags": [
      "无需动画"
    ],
    "confusion": "体检报告上常见的异常指标需不需要担心"
  },
  {
    "id": 4,
    "tags": [
      "无需动画"
    ],
    "confusion": "体检报告十几条结论看不懂，是不是全身都有病？"
  },
  {
    "id": 5,
    "tags": [
      "无需动画"
    ],
    "confusion": "体检指标异常就一定有问题吗？哪些异常其实不用担心？"
  },
  {
    "id": 6,
    "tags": [
      "肾小球滤过与肌酐代谢过程"
    ],
    "confusion": "体检肾功能报告怎么看肌酐值？"
  },
  {
    "id": 7,
    "tags": [
      "血压测量原理与血管压力示意"
    ],
    "confusion": "体检血压140/85，需不需要吃降压药？"
  },
  {
    "id": 8,
    "tags": [
      "药物与保健品在肝脏代谢过程对比"
    ],
    "confusion": "保健品是不是没有副作用，比药物更安全"
  },
  {
    "id": 9,
    "tags": [
      "免疫细胞识别与攻击病原体过程"
    ],
    "confusion": "保健品能提高免疫力吗"
  },
  {
    "id": 10,
    "tags": [
      "冠状动脉支架内血栓形成过程",
      "抗血小板药物作用机制"
    ],
    "confusion": "做完心脏支架不吃药会怎样"
  },
  {
    "id": 11,
    "tags": [
      "GLP-1受体激动剂作用机制",
      "体重反弹时脂肪细胞变化"
    ],
    "confusion": "停用减肥针后体重会反弹吗"
  },
  {
    "id": 12,
    "tags": [
      "DNA双螺旋结构与基因突变示意"
    ],
    "confusion": "健康人有没有必要做基因检测？"
  },
  {
    "id": 13,
    "tags": [
      "无需动画"
    ],
    "confusion": "健康体检到底应该做哪些项目？"
  },
  {
    "id": 14,
    "tags": [
      "药物在儿童肝肾代谢过程示意"
    ],
    "confusion": "儿童用药不当会导致什么严重后果？"
  },
  {
    "id": 15,
    "tags": [
      "免疫细胞识别与攻击病原体过程",
      "自身免疫反应攻击正常组织过程"
    ],
    "confusion": "免疫力是越强越好吗"
  },
  {
    "id": 16,
    "tags": [
      "冠状动脉内斑块形成过程",
      "冠状动脉狭窄与血流变化"
    ],
    "confusion": "关于心脏血管堵塞有哪些常见误解"
  },
  {
    "id": 17,
    "tags": [
      "新冠病毒入侵细胞过程"
    ],
    "confusion": "关于新冠的常见说法哪些是谣言？"
  },
  {
    "id": 18,
    "tags": [
      "脑动脉血栓形成与脑组织缺血过程"
    ],
    "confusion": "关于脑梗有哪些常见误区？"
  },
  {
    "id": 19,
    "tags": [
      "血液中低密度脂蛋白沉积于血管壁过程"
    ],
    "confusion": "关于血脂有哪些半真半假的谣言？"
  },
  {
    "id": 20,
    "tags": [
      "无需动画"
    ],
    "confusion": "关于饮食的常见误区有哪些"
  },
  {
    "id": 21,
    "tags": [
      "血压升高时血管壁受力示意"
    ],
    "confusion": "关于高血压有哪些常见谣言"
  },
  {
    "id": 22,
    "tags": [
      "冠状动脉狭窄与心肌缺血过程"
    ],
    "confusion": "冠心病严重吗？"
  },
  {
    "id": 23,
    "tags": [
      "冠状动脉内斑块形成过程",
      "斑块破裂引发急性心肌梗死过程"
    ],
    "confusion": "冠心病到底是慢性病还是急性病？"
  },
  {
    "id": 24,
    "tags": [
      "无需动画"
    ],
    "confusion": "冠心病常用药怎么吃（时间、空腹还是饭后、注意事项）"
  },
  {
    "id": 25,
    "tags": [
      "冠状动脉内斑块形成过程",
      "动脉粥样硬化发展全过程"
    ],
    "confusion": "冠心病是怎么得的？"
  },
  {
    "id": 26,
    "tags": [
      "无需动画"
    ],
    "confusion": "冠心病药物太多怎么办，哪些药该吃哪些不该吃"
  },
  {
    "id": 27,
    "tags": [
      "冠状动脉慢性完全闭塞与侧支循环形成",
      "经皮冠状动脉介入治疗（PCI）过程"
    ],
    "confusion": "冠状动脉慢性完全闭塞是怎么回事，怎么治疗"
  },
  {
    "id": 28,
    "tags": [
      "冠状动脉造影影像成像原理",
      "冠状动脉狭窄与血流变化"
    ],
    "confusion": "冠状动脉造影的结果怎么看？"
  },
  {
    "id": 29,
    "tags": [
      "冠脉CT三维重建成像原理",
      "冠状动脉造影影像成像原理"
    ],
    "confusion": "冠脉CT和造影哪个更准"
  },
  {
    "id": 30,
    "tags": [
      "冠状动脉狭窄与血流变化",
      "冠状动脉支架植入过程"
    ],
    "confusion": "冠脉狭窄70%的临界病变该不该放支架"
  },
  {
    "id": 31,
    "tags": [
      "冠状动脉造影影像成像原理"
    ],
    "confusion": "冠脉狭窄程度的判断是否存在主观性"
  },
  {
    "id": 32,
    "tags": [
      "冠状动脉造影影像成像原理"
    ],
    "confusion": "冠脉造影为什么看起来这么粗糙"
  },
  {
    "id": 33,
    "tags": [
      "冠状动脉造影导管从桡动脉到冠脉的路径",
      "冠状动脉造影影像成像原理"
    ],
    "confusion": "冠脉造影是怎么做的、可怕吗"
  },
  {
    "id": 34,
    "tags": [
      "冠状动脉狭窄与血流变化",
      "冠状动脉支架植入过程"
    ],
    "confusion": "冠脉重度狭窄需不需要放支架"
  },
  {
    "id": 35,
    "tags": [
      "寒冷刺激下血管收缩与血压升高过程"
    ],
    "confusion": "冬天为什么心脏病高发"
  },
  {
    "id": 36,
    "tags": [
      "寒冷刺激下血管收缩与血压升高过程",
      "运动时心脏负荷变化"
    ],
    "confusion": "冬天户外运动对心脏有什么风险？"
  },
  {
    "id": 37,
    "tags": [
      "脂肪细胞分解与能量代谢过程"
    ],
    "confusion": "减肥一定要大量出汗才有效吗？"
  },
  {
    "id": 38,
    "tags": [
      "脂肪细胞分解与能量代谢过程",
      "体重反弹时脂肪细胞变化"
    ],
    "confusion": "减肥成功后会不会反弹？反弹了怎么办？"
  },
  {
    "id": 39,
    "tags": [
      "脂肪细胞分解与能量代谢过程"
    ],
    "confusion": "减肥有哪些常见误区？"
  },
  {
    "id": 40,
    "tags": [
      "GLP-1受体激动剂作用机制",
      "体重反弹时脂肪细胞变化"
    ],
    "confusion": "减肥针停药后会不会反弹？盲目打减肥针有什么风险？"
  },
  {
    "id": 41,
    "tags": [
      "GLP-1受体激动剂作用机制"
    ],
    "confusion": "减肥针是真的有效吗、我能不能用"
  },
  {
    "id": 42,
    "tags": [
      "脑动脉血栓形成与脑组织缺血过程"
    ],
    "confusion": "刚出院为什么就脑梗了？"
  },
  {
    "id": 43,
    "tags": [
      "亚硝酸盐等致癌物损伤细胞DNA过程"
    ],
    "confusion": "加工肉类到底有多不健康"
  },
  {
    "id": 44,
    "tags": [
      "动脉斑块破裂与血栓脱落栓塞过程"
    ],
    "confusion": "动脉斑块会不会掉下来引起心梗脑梗？"
  },
  {
    "id": 45,
    "tags": [
      "动脉血栓形成过程",
      "静脉血栓形成过程"
    ],
    "confusion": "动脉血栓和静脉血栓有什么区别？"
  },
  {
    "id": 46,
    "tags": [
      "化疗药物杀伤肿瘤细胞与正常细胞过程"
    ],
    "confusion": "化疗是不是会死得更快，该不该做化疗"
  },
  {
    "id": 47,
    "tags": [
      "无需动画"
    ],
    "confusion": "化验单的参考值到底该怎么理解"
  },
  {
    "id": 48,
    "tags": [
      "免疫细胞识别与攻击病原体过程"
    ],
    "confusion": "医学上真的存在'免疫力低下'这个概念吗"
  },
  {
    "id": 49,
    "tags": [
      "无需动画"
    ],
    "confusion": "医生技术越高看病效果就越好吗？"
  },
  {
    "id": 50,
    "tags": [
      "无需动画"
    ],
    "confusion": "医生自己绝对不会踩的健康雷区有哪些"
  },
  {
    "id": 51,
    "tags": [
      "心电传导系统示意",
      "心肌缺血时心电图波形变化"
    ],
    "confusion": "单看一张心电图能不能诊断心肌缺血"
  },
  {
    "id": 52,
    "tags": [
      "新冠病毒变异株结构差异对比"
    ],
    "confusion": "南北方新冠毒株会交叉感染吗？"
  },
  {
    "id": 53,
    "tags": [
      "卵圆孔未闭时血流异常通过房间隔过程",
      "反常栓塞经卵圆孔进入脑动脉过程"
    ],
    "confusion": "卵圆孔未闭会引起偏头痛或脑梗吗"
  },
  {
    "id": 54,
    "tags": [
      "卵圆孔未闭时血流异常通过房间隔过程",
      "正常心脏房间隔结构示意"
    ],
    "confusion": "卵圆孔未闭是什么、需不需要治疗"
  },
  {
    "id": 55,
    "tags": [
      "卵圆孔未闭时血流异常通过房间隔过程",
      "卵圆孔封堵器植入过程"
    ],
    "confusion": "卵圆孔未闭需要手术吗"
  },
  {
    "id": 56,
    "tags": [
      "压迫导致周围神经缺血与传导阻滞过程"
    ],
    "confusion": "压着胳膊睡醒后剧烈麻痛是怎么回事"
  },
  {
    "id": 57,
    "tags": [
      "肠道黏膜炎症与蠕动功能紊乱示意"
    ],
    "confusion": "反复拉肚子肚子胀是怎么回事"
  },
  {
    "id": 58,
    "tags": [
      "反式脂肪酸分子结构与血管壁损伤过程"
    ],
    "confusion": "反式脂肪酸是什么，生活中怎么避开"
  },
  {
    "id": 59,
    "tags": [
      "胃食管反流时胃酸逆流过程",
      "食管下括约肌松弛示意"
    ],
    "confusion": "反酸烧心是怎么回事，怎么办？"
  },
  {
    "id": 60,
    "tags": [
      "体温调节中枢与免疫反应发热过程"
    ],
    "confusion": "发烧就一定是感冒吗？"
  },
  {
    "id": 61,
    "tags": [
      "甲状腺结节超声影像特征示意"
    ],
    "confusion": "发现甲状腺结节后应该怎么对待？"
  },
  {
    "id": 62,
    "tags": [
      "高血压对心脑肾靶器官损害过程"
    ],
    "confusion": "发现血压高只吃降压药就够了吗？"
  },
  {
    "id": 63,
    "tags": [
      "斑块破裂引发急性心肌梗死过程",
      "心肺复苏（CPR）操作示意"
    ],
    "confusion": "发生心肌梗死时怎么急救"
  },
  {
    "id": 64,
    "tags": [
      "无需动画"
    ],
    "confusion": "只吃素是不是比吃肉更健康？"
  },
  {
    "id": 65,
    "tags": [
      "动脉粥样硬化发展全过程"
    ],
    "confusion": "吃什么能软化血管？"
  },
  {
    "id": 66,
    "tags": [
      "进食过量时胃扩张与消化系统负荷示意"
    ],
    "confusion": "吃太饱对身体有什么危害"
  },
  {
    "id": 67,
    "tags": [
      "进食过量时胃扩张与消化系统负荷示意"
    ],
    "confusion": "吃太饱对身体有什么危害？"
  },
  {
    "id": 68,
    "tags": [
      "进食后消化系统与运动系统血流分配变化"
    ],
    "confusion": "吃完饭到底能不能运动"
  },
  {
    "id": 69,
    "tags": [
      "血液中低密度脂蛋白沉积于血管壁过程",
      "肝脏合成胆固醇过程"
    ],
    "confusion": "吃得越清淡血脂就越好吗"
  },
  {
    "id": 70,
    "tags": [
      "无需动画"
    ],
    "confusion": "吃药期间需要怎么复查"
  },
  {
    "id": 71,
    "tags": [
      "辅酶Q10在线粒体能量代谢中的作用"
    ],
    "confusion": "吃辅酶Q10能不能缓解"
  },
  {
    "id": 72,
    "tags": [
      "阿司匹林抗血小板聚集机制",
      "脑出血时血管破裂过程"
    ],
    "confusion": "吃阿司匹林不控制血压会导致脑出血吗"
  },
  {
    "id": 73,
    "tags": [
      "阿司匹林抗血小板聚集机制",
      "脑出血时血管破裂过程"
    ],
    "confusion": "吃阿司匹林防血栓，万一脑出血了不是更危险吗？"
  },
  {
    "id": 74,
    "tags": [
      "西柚成分抑制肝脏CYP3A4酶影响药物代谢过程"
    ],
    "confusion": "吃降压药降脂药的人能不能吃西柚"
  },
  {
    "id": 75,
    "tags": [
      "肝脏合成胆固醇过程",
      "膳食胆固醇吸收与代谢途径"
    ],
    "confusion": "吃鸡蛋要不要扔掉蛋黄，蛋黄会升高胆固醇吗"
  },
  {
    "id": 76,
    "tags": [
      "无需动画"
    ],
    "confusion": "各种药应该饭前还是饭后吃，能不能掰开"
  },
  {
    "id": 77,
    "tags": [
      "胰岛素分泌与血糖调节过程",
      "各类降糖药作用靶点示意"
    ],
    "confusion": "各种降糖药有什么区别？"
  },
  {
    "id": 78,
    "tags": [
      "各类降压药作用靶点示意"
    ],
    "confusion": "各类降压药的副作用分别是什么？"
  },
  {
    "id": 79,
    "tags": [
      "同型半胱氨酸代谢与叶酸参与甲基化过程"
    ],
    "confusion": "同型半胱氨酸高了只补叶酸就行吗？"
  },
  {
    "id": 80,
    "tags": [
      "同型半胱氨酸代谢与叶酸参与甲基化过程"
    ],
    "confusion": "同型半胱氨酸高到底要不要吃叶酸"
  },
  {
    "id": 81,
    "tags": [
      "冠状动脉侧支循环代偿示意",
      "斑块破裂引发急性心肌梗死过程"
    ],
    "confusion": "同样血管堵了50%，为什么有人没事有人心梗"
  },
  {
    "id": 82,
    "tags": [
      "心脏牵涉痛的神经传导通路示意"
    ],
    "confusion": "后背疼、肩胛骨缝疼等常见不适是不是心脏病"
  },
  {
    "id": 83,
    "tags": [
      "食管结构与吞咽过程示意",
      "食管肿瘤导致管腔狭窄示意"
    ],
    "confusion": "吞咽困难是不是就是食管癌"
  },
  {
    "id": 84,
    "tags": [
      "烟雾中有害物质损伤血管内皮过程",
      "烟雾中焦油沉积于肺泡过程"
    ],
    "confusion": "吸烟到底怎样伤害身体"
  },
  {
    "id": 85,
    "tags": [
      "无需动画"
    ],
    "confusion": "哪个年龄段的人最容易焦虑"
  },
  {
    "id": 86,
    "tags": [
      "寒冷刺激下血管收缩与血压升高过程"
    ],
    "confusion": "哪些人冬天要特别注意保暖"
  },
  {
    "id": 87,
    "tags": [
      "心房颤动时心房内血栓形成过程",
      "血栓脱落经颈动脉栓塞脑动脉过程"
    ],
    "confusion": "哪些人最容易发生脑梗？房颤为什么会导致脑梗？"
  },
  {
    "id": 88,
    "tags": [
      "无需动画"
    ],
    "confusion": "哪些体检项目其实没必要做？"
  },
  {
    "id": 89,
    "tags": [
      "无需动画"
    ],
    "confusion": "哪些医学科普观点容易被断章取义误解？"
  },
  {
    "id": 90,
    "tags": [
      "脑动脉血栓形成与脑组织缺血过程"
    ],
    "confusion": "哪些容易忽视的因素会导致脑梗？"
  },
  {
    "id": 91,
    "tags": [
      "无需动画"
    ],
    "confusion": "哪些常用药容易被滥用/错用？"
  },
  {
    "id": 92,
    "tags": [
      "动脉粥样硬化发展全过程"
    ],
    "confusion": "哪些常见保健品和做法其实没用（软化血管、水蛭素等）"
  },
  {
    "id": 93,
    "tags": [
      "动脉粥样硬化发展全过程"
    ],
    "confusion": "哪些常见早餐会堵塞血管？"
  },
  {
    "id": 94,
    "tags": [
      "无需动画"
    ],
    "confusion": "哪些常见的健康养生说法其实是伪科学"
  },
  {
    "id": 95,
    "tags": [
      "药物在肝肾代谢与蓄积过程"
    ],
    "confusion": "哪些常见药不能长期吃"
  },
  {
    "id": 96,
    "tags": [
      "药物在儿童肝肾代谢过程示意"
    ],
    "confusion": "哪些常见药大人能吃但对小孩危险"
  },
  {
    "id": 97,
    "tags": [
      "肾小球滤过与肾单位损伤过程"
    ],
    "confusion": "哪些日常习惯会伤肾、导致尿毒症"
  },
  {
    "id": 98,
    "tags": [
      "肾小球滤过与肾单位损伤过程"
    ],
    "confusion": "哪些日常习惯会伤肾？"
  },
  {
    "id": 99,
    "tags": [
      "无需动画"
    ],
    "confusion": "哪些水果脂肪含量高、越吃越胖"
  },
  {
    "id": 100,
    "tags": [
      "血液中低密度脂蛋白沉积于血管壁过程",
      "肝脏合成胆固醇过程"
    ],
    "confusion": "哪些疾病和饮食因素会升高血脂"
  },
  {
    "id": 101,
    "tags": [
      "无需动画"
    ],
    "confusion": "哪些症状容易被误认为正常衰老，其实是疾病信号？"
  },
  {
    "id": 102,
    "tags": [
      "无需动画"
    ],
    "confusion": "哪些症状必须去医院，哪些不用担心？"
  },
  {
    "id": 103,
    "tags": [
      "无需动画"
    ],
    "confusion": "哪些看似健康的食品其实不健康？"
  },
  {
    "id": 104,
    "tags": [
      "无需动画"
    ],
    "confusion": "哪些看起来健康的食物其实不健康"
  },
  {
    "id": 105,
    "tags": [
      "无需动画"
    ],
    "confusion": "哪些肉可以放心吃，怎么选肉最健康？"
  },
  {
    "id": 106,
    "tags": [
      "药物在儿童肝肾代谢过程示意"
    ],
    "confusion": "哪些药不能随便给小孩吃"
  },
  {
    "id": 107,
    "tags": [
      "无需动画"
    ],
    "confusion": "哪些身体变化是正常衰老而非疾病"
  },
  {
    "id": 108,
    "tags": [
      "胰岛素抵抗时细胞对葡萄糖摄取障碍过程",
      "运动时肌肉能量代谢过程"
    ],
    "confusion": "哪些运动反而会加重胰岛素抵抗导致越减越肥"
  },
  {
    "id": 109,
    "tags": [
      "动脉粥样硬化发展全过程",
      "血液中低密度脂蛋白沉积于血管壁过程"
    ],
    "confusion": "哪些饮食习惯真正导致血管堵塞？"
  },
  {
    "id": 110,
    "tags": [
      "乙醛在肝脏代谢与肝细胞损伤过程",
      "肝细胞癌变过程"
    ],
    "confusion": "哪种喝酒反应对身体损害最大最易得肝癌"
  },
  {
    "id": 111,
    "tags": [
      "无需动画"
    ],
    "confusion": "喝汤到底有没有营养？"
  },
  {
    "id": 112,
    "tags": [
      "无需动画"
    ],
    "confusion": "喝茶到底健不健康"
  },
  {
    "id": 113,
    "tags": [
      "酒精在肝脏代谢转化为脂肪的过程",
      "脂肪在肝细胞内堆积过程"
    ],
    "confusion": "喝酒又不是喝脂肪，为什么会引起脂肪肝"
  },
  {
    "id": 114,
    "tags": [
      "酒精在肝脏代谢转化为脂肪的过程",
      "脂肪在肝细胞内堆积过程"
    ],
    "confusion": "喝酒又不是喝脂肪，为什么会得脂肪肝？"
  },
  {
    "id": 115,
    "tags": [
      "乙醛在肝脏代谢与肝细胞损伤过程"
    ],
    "confusion": "喝酒怎么才能少伤身、不容易醉？"
  },
  {
    "id": 116,
    "tags": [
      "乙醛脱氢酶代谢乙醛过程",
      "面部毛细血管扩张示意"
    ],
    "confusion": "喝酒脸红、脸白、出汗哪种最能喝"
  },
  {
    "id": 117,
    "tags": [
      "血液中血红蛋白氧合与脱氧变化示意"
    ],
    "confusion": "嘴唇发紫是不是心脏病的表现"
  },
  {
    "id": 118,
    "tags": [
      "无需动画"
    ],
    "confusion": "地中海饮食是什么，对心血管真的有好处吗"
  },
  {
    "id": 119,
    "tags": [
      "多种药物在肝脏竞争代谢酶过程"
    ],
    "confusion": "多种药物一起吃身体受得了吗"
  },
  {
    "id": 120,
    "tags": [
      "肾小球滤过与肌酐代谢过程",
      "心力衰竭时肾脏血流灌注变化"
    ],
    "confusion": "夜尿增多是肾虚还是心脏问题？一晚尿几次算正常？"
  },
  {
    "id": 121,
    "tags": [
      "膝关节软骨受力与磨损过程"
    ],
    "confusion": "大体重的人怕伤膝盖不敢运动，怎么减肥？"
  },
  {
    "id": 122,
    "tags": [
      "结直肠黏膜息肉癌变过程"
    ],
    "confusion": "大肠癌有哪些早期信号"
  },
  {
    "id": 123,
    "tags": [
      "血压升高时血管壁受力示意"
    ],
    "confusion": "天气热了血压变低，降压药要不要调整？"
  },
  {
    "id": 124,
    "tags": [
      "睡眠周期中大脑神经活动变化"
    ],
    "confusion": "失眠对身体的危害能补救吗"
  },
  {
    "id": 125,
    "tags": [
      "头孢类药物抑制乙醛脱氢酶导致乙醛蓄积过程"
    ],
    "confusion": "头孢配酒为什么会致命"
  },
  {
    "id": 126,
    "tags": [
      "前庭系统与平衡感觉传导通路示意"
    ],
    "confusion": "头晕查不出原因怎么办，可能是什么病"
  },
  {
    "id": 127,
    "tags": [
      "女性尿道解剖结构与细菌上行感染过程"
    ],
    "confusion": "女性为什么更容易泌尿系感染"
  },
  {
    "id": 128,
    "tags": [
      "乳腺组织癌变过程示意"
    ],
    "confusion": "女性最容易得的癌症是什么？"
  },
  {
    "id": 129,
    "tags": [
      "红细胞生成与血红蛋白合成过程"
    ],
    "confusion": "女性贫血气色差怎么补血？"
  },
  {
    "id": 130,
    "tags": [
      "自主神经系统（交感与副交感）调节示意"
    ],
    "confusion": "好好的人怎么突然就得了植物神经紊乱"
  },
  {
    "id": 131,
    "tags": [
      "冠状动脉内斑块形成过程",
      "心肌缺血时心电图波形变化"
    ],
    "confusion": "如何在心梗前早期发现心脏问题"
  },
  {
    "id": 132,
    "tags": [
      "脑动脉血栓形成与脑组织缺血过程"
    ],
    "confusion": "如何快速识别脑卒中"
  },
  {
    "id": 133,
    "tags": [
      "冠状动脉狭窄与心肌缺血过程"
    ],
    "confusion": "如何评估自己心脏的健康年龄"
  },
  {
    "id": 134,
    "tags": [
      "胰岛素分泌与血糖调节过程"
    ],
    "confusion": "如何远离糖尿病？"
  },
  {
    "id": 135,
    "tags": [
      "熬夜时交感神经持续兴奋与心脏负荷变化",
      "心脏电传导异常导致心律失常过程"
    ],
    "confusion": "如何避免熬夜导致的猝死"
  },
  {
    "id": 136,
    "tags": [
      "高血糖损伤微血管与神经末梢过程",
      "糖尿病肾病肾小球硬化过程"
    ],
    "confusion": "如何避免糖尿病并发症"
  },
  {
    "id": 137,
    "tags": [
      "心脏电传导异常导致心律失常过程",
      "心肺复苏（CPR）操作示意",
      "自动体外除颤器（AED）除颤过程"
    ],
    "confusion": "如何预防和抢救心脏骤停？"
  },
  {
    "id": 138,
    "tags": [
      "肾结石在肾盂与输尿管形成过程"
    ],
    "confusion": "如何预防肾结石"
  },
  {
    "id": 139,
    "tags": [
      "体温调节中枢与免疫反应发热过程"
    ],
    "confusion": "学龄前儿童发烧怎么办"
  },
  {
    "id": 140,
    "tags": [
      "热性惊厥时大脑神经元异常放电过程"
    ],
    "confusion": "孩子发烧抽搐（热性惊厥）怎么正确急救？"
  },
  {
    "id": 141,
    "tags": [
      "心脏电传导系统示意",
      "房室结折返性心动过速发生机制"
    ],
    "confusion": "室上性心动过速是怎么回事"
  },
  {
    "id": 142,
    "tags": [
      "新冠病毒入侵细胞过程"
    ],
    "confusion": "家里有老人面对新冠该怎么应对？为什么不能躺平？"
  },
  {
    "id": 143,
    "tags": [
      "新冠病毒入侵细胞过程"
    ],
    "confusion": "家里老人还没阳，该怎么提前准备和保护？"
  },
  {
    "id": 144,
    "tags": [
      "体温调节中枢与免疫反应发热过程"
    ],
    "confusion": "小孩发烧什么时候需要去医院"
  },
  {
    "id": 145,
    "tags": [
      "无需动画"
    ],
    "confusion": "小孩感冒了到底要不要吃药"
  },
  {
    "id": 146,
    "tags": [
      "新冠病毒入侵细胞过程"
    ],
    "confusion": "小孩感染新冠怎么防护和治疗？"
  },
  {
    "id": 147,
    "tags": [
      "维生素A维持视网膜感光细胞功能示意",
      "维生素D促进钙吸收与骨骼发育过程"
    ],
    "confusion": "小孩需不需要额外补充维生素A和D"
  },
  {
    "id": 148,
    "tags": [
      "颈动脉斑块形成过程",
      "肝脏合成胆固醇过程"
    ],
    "confusion": "少吃油就能避免颈动脉斑块吗"
  },
  {
    "id": 149,
    "tags": [
      "肾小球滤过与肌酐代谢过程"
    ],
    "confusion": "尿常规报告怎么看？那些箭头是什么意思？"
  },
  {
    "id": 150,
    "tags": [
      "尿酸在关节腔沉积形成痛风结晶过程",
      "嘌呤代谢与尿酸生成过程"
    ],
    "confusion": "尿酸升高是不是不能吃海鲜了"
  },
  {
    "id": 1,
    "tags": [
      "血液尿酸水平与肾脏排泄机制",
      "高尿酸血症对肾脏和关节的损害过程"
    ],
    "confusion": "尿酸只是偏高一点需不需要吃药"
  },
  {
    "id": 2,
    "tags": [
      "嘌呤代谢与尿酸生成pathway",
      "高嘌呤食物在体内的代谢过程"
    ],
    "confusion": "尿酸高/痛风到底应该怎么吃"
  },
  {
    "id": 3,
    "tags": [
      "高尿酸血症对肾脏和关节的隐匿性损害过程",
      "尿酸盐结晶在关节中沉积过程"
    ],
    "confusion": "尿酸高但没有痛风症状需不需要吃药"
  },
  {
    "id": 4,
    "tags": [
      "血液尿酸水平与肾脏排泄机制",
      "尿酸盐结晶在关节和肾脏中沉积过程"
    ],
    "confusion": "尿酸高到底要不要吃药，什么时候必须吃"
  },
  {
    "id": 5,
    "tags": [
      "嘌呤代谢与尿酸生成pathway",
      "肝脏合成嘌呤与肾脏排泄尿酸的平衡机制"
    ],
    "confusion": "尿酸高是不是因为吃了太多高嘌呤食物？"
  },
  {
    "id": 6,
    "tags": [
      "肾小球滤过机制与蛋白尿形成",
      "尿液中蛋白质产生泡沫的原理"
    ],
    "confusion": "尿里有泡沫是不是说明肾不好"
  },
  {
    "id": 7,
    "tags": [
      "主动脉弓分支结构与左右上肢供血差异",
      "血压测量原理示意"
    ],
    "confusion": "左右手血压不一样怎么回事？算不算高血压？"
  },
  {
    "id": 8,
    "tags": [
      "无需动画"
    ],
    "confusion": "市售电解质水真的有用吗？"
  },
  {
    "id": 9,
    "tags": [
      "无需动画"
    ],
    "confusion": "常见体检套餐哪些项目有用哪些没用？"
  },
  {
    "id": 10,
    "tags": [
      "心脏整体结构与常见心脏病分类示意"
    ],
    "confusion": "常见心脏病认知误区有哪些"
  },
  {
    "id": 11,
    "tags": [
      "无需动画"
    ],
    "confusion": "常见的健康误区有哪些"
  },
  {
    "id": 12,
    "tags": [
      "无需动画"
    ],
    "confusion": "常见的减肥误区有哪些？"
  },
  {
    "id": 13,
    "tags": [
      "无需动画"
    ],
    "confusion": "常见的运动误区有哪些"
  },
  {
    "id": 14,
    "tags": [
      "无需动画"
    ],
    "confusion": "常见育儿健康谣言有哪些（补钙长高等）"
  },
  {
    "id": 15,
    "tags": [
      "心脏泵血功能下降与心输出量减少过程",
      "心脏传导系统异常导致心律失常"
    ],
    "confusion": "年纪大了容易心慌胸闷体力下降是心脏病吗？"
  },
  {
    "id": 16,
    "tags": [
      "冠状动脉内斑块形成过程",
      "年轻人冠状动脉粥样硬化与斑块破裂"
    ],
    "confusion": "年轻人为什么也会血管堵塞需要放支架？"
  },
  {
    "id": 17,
    "tags": [
      "血压调节机制示意"
    ],
    "confusion": "年轻人为什么高血压控制率反而不如老年人"
  },
  {
    "id": 18,
    "tags": [
      "冠状动脉内血栓形成导致心肌梗死过程",
      "心肌梗死急救——冠脉介入手术过程"
    ],
    "confusion": "年轻人也会心梗吗，心梗来了怎么抢救"
  },
  {
    "id": 19,
    "tags": [
      "心脏传导系统异常导致室颤",
      "肥厚型心肌病心肌结构异常示意",
      "冠状动脉内血栓形成导致心肌梗死过程"
    ],
    "confusion": "年轻人心源性猝死可能是哪些原因？"
  },
  {
    "id": 20,
    "tags": [
      "心脏传导系统异常导致室颤",
      "冠状动脉内血栓形成导致心肌梗死过程"
    ],
    "confusion": "年轻人猝死最常见的原因是什么"
  },
  {
    "id": 21,
    "tags": [
      "肾上腺与肾动脉异常导致继发性高血压机制",
      "血压调节机制示意"
    ],
    "confusion": "年轻人血压高一定是高血压病吗？"
  },
  {
    "id": 22,
    "tags": [
      "低密度脂蛋白在血管壁沉积形成斑块过程",
      "动脉粥样硬化从脂纹到斑块的演变"
    ],
    "confusion": "年轻人需要关注胆固醇吗"
  },
  {
    "id": 23,
    "tags": [
      "长期高血压对心脑肾靶器官损害过程",
      "左心室肥厚与心衰发展过程"
    ],
    "confusion": "年轻人高血压不吃药会怎样"
  },
  {
    "id": 24,
    "tags": [
      "肾上腺与肾动脉异常导致继发性高血压机制",
      "多种降压药作用靶点示意"
    ],
    "confusion": "年轻人高血压吃多种药还控制不住是怎么回事？"
  },
  {
    "id": 25,
    "tags": [
      "脑血管闭塞导致脑组织缺血坏死过程",
      "脑动脉内血栓形成或栓子脱落过程"
    ],
    "confusion": "年轻人（90后）也会得脑卒中吗"
  },
  {
    "id": 26,
    "tags": [
      "动脉粥样硬化从脂纹到斑块的长期演变",
      "长期高血压对心脑肾靶器官损害过程"
    ],
    "confusion": "年轻时不锻炼不体检，未来要付出多大的健康代价？"
  },
  {
    "id": 27,
    "tags": [
      "幽门螺杆菌在胃黏膜定植与破坏过程",
      "胃黏膜从炎症到萎缩到癌变的演变"
    ],
    "confusion": "幽门螺杆菌到底要不要治？"
  },
  {
    "id": 28,
    "tags": [
      "高血糖对血管和神经的微观损害过程",
      "糖尿病并发症——视网膜、肾脏、神经病变示意"
    ],
    "confusion": "得了糖尿病到底意味着什么，并发症多久会出现"
  },
  {
    "id": 29,
    "tags": [
      "长期高血压对心脑肾靶器官损害过程",
      "降压药作用靶点示意"
    ],
    "confusion": "得了高血压是不是真的要终身吃药"
  },
  {
    "id": 30,
    "tags": [
      "高血压对心脏、肾脏、眼底、血管的靶器官损害",
      "心脏彩超和肾功能检查原理示意"
    ],
    "confusion": "得了高血压除了吃药还需要做哪些检查"
  },
  {
    "id": 31,
    "tags": [
      "无需动画"
    ],
    "confusion": "得了高血压饮食上应该怎么吃"
  },
  {
    "id": 32,
    "tags": [
      "微创介入手术路径示意",
      "开胸手术与微创手术对比"
    ],
    "confusion": "微创手术是不是比开胸手术风险更小"
  },
  {
    "id": 33,
    "tags": [
      "自主神经功能紊乱对心脏和消化系统的影响",
      "交感神经与副交感神经调节示意"
    ],
    "confusion": "心慌、出汗、腹泻等症状查不出器质性问题，是什么原因？"
  },
  {
    "id": 34,
    "tags": [
      "心脏传导系统示意",
      "早搏在心脏传导中的发生机制"
    ],
    "confusion": "心慌早搏心跳不齐是怎么回事、原理是什么"
  },
  {
    "id": 35,
    "tags": [
      "心脏传导系统示意",
      "早搏与室颤的区别示意"
    ],
    "confusion": "心慌是不是心脏病，会不会猝死"
  },
  {
    "id": 36,
    "tags": [
      "心脏传导系统示意",
      "早搏在心脏传导中的发生机制",
      "心房颤动时心房电信号紊乱示意"
    ],
    "confusion": "心慌是什么原因？早搏和房颤是怎么回事？"
  },
  {
    "id": 37,
    "tags": [
      "自主神经功能紊乱对心脏的影响",
      "焦虑情绪通过神经内分泌系统引发心脏症状"
    ],
    "confusion": "心慌胸闷为什么总是查不出原因"
  },
  {
    "id": 38,
    "tags": [
      "心肌梗死急救——冠脉介入手术过程",
      "心肌梗死发生后心肌坏死随时间扩展"
    ],
    "confusion": "心梗了应该就近治疗还是转院去大医院？"
  },
  {
    "id": 39,
    "tags": [
      "冠脉支架植入术过程",
      "冠状动脉内血栓形成导致心肌梗死过程"
    ],
    "confusion": "心梗了该不该拒绝放支架？"
  },
  {
    "id": 40,
    "tags": [
      "冠状动脉内斑块从稳定到破裂的过程",
      "斑块破裂后血栓形成堵塞冠脉"
    ],
    "confusion": "心梗到底是怎么发生的？是斑块慢慢长满堵死的吗？"
  },
  {
    "id": 41,
    "tags": [
      "冠状动脉内斑块从稳定到破裂的过程",
      "心肌缺血引发胸痛放射痛的神经传导"
    ],
    "confusion": "心梗发作前有哪些信号/征兆？"
  },
  {
    "id": 42,
    "tags": [
      "冠状动脉内斑块从稳定到破裂的过程",
      "心肌缺血引发胸痛放射痛的神经传导"
    ],
    "confusion": "心梗发作前有哪些信号？"
  },
  {
    "id": 43,
    "tags": [
      "斑块破裂后血小板聚集形成血栓过程",
      "阿司匹林抑制血小板聚集的药理机制"
    ],
    "confusion": "心梗发作时是否应该嚼服阿司匹林"
  },
  {
    "id": 44,
    "tags": [
      "清晨血压波动与交感神经激活机制",
      "清晨血液黏稠度升高与血栓形成"
    ],
    "confusion": "心梗和脑梗为什么容易发生在清晨"
  },
  {
    "id": 45,
    "tags": [
      "β受体阻滞剂对心脏的保护机制",
      "心梗后心室重构过程"
    ],
    "confusion": "心梗康复后长期吃的β受体阻滞剂还有没有必要继续吃？"
  },
  {
    "id": 46,
    "tags": [
      "大面积心肌梗死导致心源性休克过程",
      "心室颤动导致心脏骤停机制"
    ],
    "confusion": "心梗患者为什么有时救不过来"
  },
  {
    "id": 47,
    "tags": [
      "冠状动脉内斑块破裂与血栓形成导致心肌梗死"
    ],
    "confusion": "心梗是怎么发生的"
  },
  {
    "id": 48,
    "tags": [
      "冠状动脉内斑块破裂与血栓形成导致心肌梗死"
    ],
    "confusion": "心梗是怎么发生的？"
  },
  {
    "id": 49,
    "tags": [
      "冠状动脉内斑块从稳定到破裂的过程",
      "心肌缺血引发胸痛放射痛的神经传导"
    ],
    "confusion": "心梗的前兆是什么"
  },
  {
    "id": 50,
    "tags": [
      "冠状动脉钙化积分CT扫描原理",
      "易损斑块的影像学特征"
    ],
    "confusion": "心梗能不能提前预测"
  },
  {
    "id": 51,
    "tags": [
      "窦房结自律性与心率调节机制"
    ],
    "confusion": "心率60-100次是正常范围，超出就不正常吗"
  },
  {
    "id": 52,
    "tags": [
      "窦房结自律性与心率调节机制",
      "心脏传导系统示意"
    ],
    "confusion": "心率只有50多次是不是太慢了？需要治疗吗？"
  },
  {
    "id": 53,
    "tags": [
      "交感神经激活导致心率加快与血压升高",
      "血压调节机制示意"
    ],
    "confusion": "心率快时血压升高需要加药吗"
  },
  {
    "id": 54,
    "tags": [
      "窦房结自律性与心率调节机制",
      "心率与心肌耗氧量的关系"
    ],
    "confusion": "心率慢是好事还是坏事？心率和寿命有什么关系？"
  },
  {
    "id": 55,
    "tags": [
      "甲状腺激素对心脏和神经系统的作用机制",
      "交感神经兴奋导致心率加快与手抖"
    ],
    "confusion": "心率过快伴手抖是什么原因"
  },
  {
    "id": 56,
    "tags": [
      "心电图T波形成原理与心肌复极过程",
      "心肌缺血时心电图ST-T改变机制"
    ],
    "confusion": "心电图T波改变就是心肌缺血吗，会不会是其他疾病"
  },
  {
    "id": 57,
    "tags": [
      "心电图检测心脏电活动原理",
      "心脏彩超检测心脏结构与功能原理",
      "冠脉造影显示血管狭窄程度原理"
    ],
    "confusion": "心电图和心脏彩超没问题为什么还要做冠脉造影"
  },
  {
    "id": 58,
    "tags": [
      "心脏传导系统示意",
      "预激综合征旁路传导通路示意"
    ],
    "confusion": "心电图异常预激综合征需要治疗吗"
  },
  {
    "id": 59,
    "tags": [
      "心电图各波形对应心脏电活动示意"
    ],
    "confusion": "心电图报告结论一大堆，哪些有问题哪些没问题？"
  },
  {
    "id": 60,
    "tags": [
      "心电图T波形成原理与心肌复极过程",
      "心肌缺血时心电图ST-T改变机制"
    ],
    "confusion": "心电图提示心肌缺血就真的是心肌缺血吗"
  },
  {
    "id": 61,
    "tags": [
      "心肌缺血时心电图ST-T改变机制",
      "冠状动脉狭窄导致心肌供血不足"
    ],
    "confusion": "心电图显示心肌缺血该怎么办"
  },
  {
    "id": 62,
    "tags": [
      "心电图检测心脏电活动原理",
      "冠状动脉狭窄导致心肌供血不足"
    ],
    "confusion": "心电图有问题是不是就说明心脏血管堵了"
  },
  {
    "id": 63,
    "tags": [
      "冠状动脉狭窄导致心肌供血不足",
      "心肌缺血引发胸痛放射痛的神经传导"
    ],
    "confusion": "心绞痛到底是什么感觉"
  },
  {
    "id": 64,
    "tags": [
      "心肌桥——冠状动脉被心肌覆盖的解剖结构",
      "心肌收缩时冠脉受压狭窄的动态过程"
    ],
    "confusion": "心肌桥是什么，严不严重，需要治疗吗"
  },
  {
    "id": 65,
    "tags": [
      "冠状动脉内斑块破裂与血栓形成导致心肌梗死"
    ],
    "confusion": "心肌梗死到底是怎么发生的"
  },
  {
    "id": 66,
    "tags": [
      "冠脉支架植入术过程",
      "冠状动脉内血栓形成导致心肌梗死过程"
    ],
    "confusion": "心肌梗死是不是一定要放支架"
  },
  {
    "id": 67,
    "tags": [
      "动脉粥样硬化从脂纹到斑块的演变",
      "冠状动脉内斑块从稳定到破裂的过程"
    ],
    "confusion": "心肌梗死是怎么一步步发展的，能否在早期逆转"
  },
  {
    "id": 68,
    "tags": [
      "大面积心肌梗死导致心源性休克过程",
      "心室颤动导致心脏骤停机制",
      "心梗后心室重构与心衰发展"
    ],
    "confusion": "心肌梗死最可怕的后果是什么"
  },
  {
    "id": 69,
    "tags": [
      "冠状动脉内斑块从稳定到破裂的过程",
      "心肌缺血引发胸痛放射痛的神经传导"
    ],
    "confusion": "心肌梗死的征兆是什么"
  },
  {
    "id": 70,
    "tags": [
      "冠脉支架植入术过程",
      "溶栓药物溶解冠脉内血栓过程",
      "冠状动脉搭桥手术过程"
    ],
    "confusion": "心肌梗死的治疗手段是怎么发展过来的？"
  },
  {
    "id": 71,
    "tags": [
      "冠状动脉侧支循环代偿机制",
      "心肌缺血但无症状的神经传导差异"
    ],
    "confusion": "心肌缺血为什么可以没有症状"
  },
  {
    "id": 72,
    "tags": [
      "冠状动脉狭窄导致心肌供血不足",
      "心肌细胞缺氧时的代谢变化"
    ],
    "confusion": "心肌缺血到底是什么意思"
  },
  {
    "id": 73,
    "tags": [
      "冠状动脉微循环障碍示意",
      "心脏神经官能症的神经调节异常"
    ],
    "confusion": "心脏不舒服但血管没严重堵塞，是怎么回事？"
  },
  {
    "id": 74,
    "tags": [
      "心脏康复运动时心肌供血与侧支循环改善"
    ],
    "confusion": "心脏出问题后是不是应该静养少动？"
  },
  {
    "id": 75,
    "tags": [
      "可吸收支架植入与降解过程",
      "冠脉支架植入术过程"
    ],
    "confusion": "心脏可吸收支架效果怎么样，适合哪些人"
  },
  {
    "id": 76,
    "tags": [
      "心脏彩超检测心脏结构与功能原理"
    ],
    "confusion": "心脏彩超报告上的异常是否都是严重心脏病"
  },
  {
    "id": 77,
    "tags": [
      "心脏彩超检测心脏结构与功能原理",
      "心脏四腔结构与瓣膜运动示意"
    ],
    "confusion": "心脏彩超报告上那么多数据和结论该怎么看"
  },
  {
    "id": 78,
    "tags": [
      "心脏彩超检测心脏结构与功能原理",
      "左室射血分数测量原理"
    ],
    "confusion": "心脏彩超报告怎么看，哪个指标最重要"
  },
  {
    "id": 79,
    "tags": [
      "心脏彩超检测心脏结构与功能原理",
      "心脏四腔结构与瓣膜运动示意"
    ],
    "confusion": "心脏彩超报告那么多数字和结论，怎么看？"
  },
  {
    "id": 80,
    "tags": [
      "冠状动脉搭桥手术过程"
    ],
    "confusion": "心脏搭桥手术是怎么做的"
  },
  {
    "id": 81,
    "tags": [
      "冠状动脉搭桥手术过程"
    ],
    "confusion": "心脏搭桥手术是怎么做的？"
  },
  {
    "id": 82,
    "tags": [
      "冠脉支架植入术过程",
      "支架内再狭窄与内皮化过程"
    ],
    "confusion": "心脏支架到底该不该放，放了有什么影响"
  },
  {
    "id": 83,
    "tags": [
      "冠脉支架植入术过程"
    ],
    "confusion": "心脏支架手术是怎么做的？"
  },
  {
    "id": 84,
    "tags": [
      "支架内再狭窄与内皮化过程",
      "药物洗脱支架药物释放机制"
    ],
    "confusion": "心脏支架是不是只有十年寿命？"
  },
  {
    "id": 85,
    "tags": [
      "支架内再狭窄与内皮化过程",
      "支架被内皮细胞覆盖后无法取出的原因"
    ],
    "confusion": "心脏支架能不能取出来、为什么不普及取出技术"
  },
  {
    "id": 86,
    "tags": [
      "早搏在心脏传导中的发生机制",
      "心脏传导系统示意"
    ],
    "confusion": "心脏早搏可怕吗"
  },
  {
    "id": 87,
    "tags": [
      "常见心脏药物作用靶点示意"
    ],
    "confusion": "心脏病人常见的用药误区有哪些？"
  },
  {
    "id": 88,
    "tags": [
      "心脏整体结构与常见心脏病分类示意",
      "冠心病、心律失常、心肌病、瓣膜病对比"
    ],
    "confusion": "心脏病到底有哪几种、是怎么回事？"
  },
  {
    "id": 89,
    "tags": [
      "冠状动脉内斑块从稳定到破裂的过程",
      "心肌缺血引发胸痛放射痛的神经传导"
    ],
    "confusion": "心脏病发作前有哪些求救信号"
  },
  {
    "id": 90,
    "tags": [
      "常见心脏药物作用靶点示意"
    ],
    "confusion": "心脏科常用的药各有什么作用？哪些要长期吃哪些是过渡？"
  },
  {
    "id": 91,
    "tags": [
      "冠状动脉解剖结构与分支走行",
      "冠状动脉狭窄导致心肌供血不足"
    ],
    "confusion": "心脏血管的结构是怎样的，心肌缺血是怎么回事"
  },
  {
    "id": 92,
    "tags": [
      "冠脉造影导管从桡动脉到冠脉的路径",
      "冠脉造影显示血管狭窄程度原理"
    ],
    "confusion": "心脏造影风险到底有多大？"
  },
  {
    "id": 93,
    "tags": [
      "急性心衰时肺水肿形成机制",
      "心衰急救——利尿与强心药物作用机制"
    ],
    "confusion": "心衰发作时如何急救"
  },
  {
    "id": 94,
    "tags": [
      "心衰时心脏泵血功能下降与神经内分泌激活",
      "心衰药物四联疗法作用靶点"
    ],
    "confusion": "心衰应该怎么规范治疗"
  },
  {
    "id": 95,
    "tags": [
      "心衰时心室扩张与泵血效率下降过程",
      "心脏扩大后瓣膜关闭不全导致反流"
    ],
    "confusion": "心衰是怎么回事，心脏变大为什么反而更危险？"
  },
  {
    "id": 96,
    "tags": [
      "心衰时心室扩张与泵血效率下降过程",
      "心衰药物四联疗法作用靶点"
    ],
    "confusion": "心衰能治好吗"
  },
  {
    "id": 97,
    "tags": [
      "迷走神经刺激降低心率的机制",
      "瓦尔萨尔瓦动作对心脏的作用原理"
    ],
    "confusion": "心跳突然加快时如何快速降低心率"
  },
  {
    "id": 98,
    "tags": [
      "快速减肥时肌肉流失与代谢率下降过程",
      "胆囊结石在快速减重中的形成机制"
    ],
    "confusion": "快速减肥有什么风险？"
  },
  {
    "id": 99,
    "tags": [
      "心电图检测心脏电活动原理",
      "心脏彩超检测心脏结构与功能原理",
      "冠脉造影显示血管狭窄程度原理"
    ],
    "confusion": "怀疑心脏有问题应该做哪些检查"
  },
  {
    "id": 100,
    "tags": [
      "肾小球滤过机制",
      "肌酐和尿素氮在肾脏中的代谢过程"
    ],
    "confusion": "怎么从化验报告看自己的肾功能是否正常"
  },
  {
    "id": 101,
    "tags": [
      "肝脏合成与代谢胆固醇的过程",
      "他汀类药物在肝脏中抑制胆固醇合成"
    ],
    "confusion": "怎么保护肝脏来降血脂？"
  },
  {
    "id": 102,
    "tags": [
      "动脉粥样硬化从脂纹到斑块的演变",
      "冠状动脉内斑块破裂与血栓形成导致心肌梗死"
    ],
    "confusion": "怎么做才能预防心梗脑梗？"
  },
  {
    "id": 103,
    "tags": [
      "无需动画"
    ],
    "confusion": "怎么判断一项检查有没有必要做"
  },
  {
    "id": 104,
    "tags": [
      "无需动画"
    ],
    "confusion": "怎么判断自己蛋白质够不够？"
  },
  {
    "id": 105,
    "tags": [
      "脑血管闭塞导致脑组织缺血坏死过程"
    ],
    "confusion": "怎么快速识别身边人是不是脑梗了？"
  },
  {
    "id": 106,
    "tags": [
      "胰岛素与细胞表面受体结合调节血糖过程",
      "胰岛素抵抗时细胞对胰岛素反应减弱"
    ],
    "confusion": "怎么检查自己有没有胰岛素抵抗？"
  },
  {
    "id": 107,
    "tags": [
      "甲状腺激素分泌与下丘脑-垂体-甲状腺轴调节"
    ],
    "confusion": "怎么评估甲状腺功能"
  },
  {
    "id": 108,
    "tags": [
      "颈动脉超声检测斑块原理",
      "冠状动脉钙化积分CT扫描原理"
    ],
    "confusion": "怎么通过体检了解自己血管状态来预防心梗"
  },
  {
    "id": 109,
    "tags": [
      "骨质疏松时骨小梁变稀疏的微观变化",
      "破骨细胞与成骨细胞的骨代谢平衡"
    ],
    "confusion": "怎么预防骨质疏松"
  },
  {
    "id": 110,
    "tags": [
      "动脉粥样硬化从脂纹到斑块的演变",
      "冠状动脉内斑块破裂与血栓形成导致心肌梗死"
    ],
    "confusion": "怎样做才能预防心梗脑梗、健康长寿"
  },
  {
    "id": 111,
    "tags": [
      "动脉粥样硬化从脂纹到斑块的演变",
      "冠状动脉内斑块破裂与血栓形成导致心肌梗死"
    ],
    "confusion": "怎样做才能预防心梗脑梗？"
  },
  {
    "id": 112,
    "tags": [
      "胆汁在胆囊中浓缩与胆结石形成过程"
    ],
    "confusion": "怎样做才能预防胆结石？"
  },
  {
    "id": 113,
    "tags": [
      "基础代谢率与肌肉量的关系",
      "快速减肥时肌肉流失与代谢率下降过程"
    ],
    "confusion": "怎样减肥才不伤害代谢"
  },
  {
    "id": 114,
    "tags": [
      "血压测量原理示意"
    ],
    "confusion": "怎样才算准确测量血压"
  },
  {
    "id": 115,
    "tags": [
      "无需动画"
    ],
    "confusion": "怎样才算熬夜，每天应该睡多久"
  },
  {
    "id": 116,
    "tags": [
      "无需动画"
    ],
    "confusion": "思诺思（唑吡坦）是什么药？会上瘾吗？算禁药吗？"
  },
  {
    "id": 117,
    "tags": [
      "心肌梗死急救——冠脉介入手术过程",
      "导管从桡动脉到冠脉的路径"
    ],
    "confusion": "急性心梗的介入手术是怎么做的？"
  },
  {
    "id": 118,
    "tags": [
      "无需动画"
    ],
    "confusion": "总担心自己得了大病是不是疑病症"
  },
  {
    "id": 119,
    "tags": [
      "红细胞生成与血红蛋白携氧机制",
      "贫血时组织缺氧的全身影响"
    ],
    "confusion": "总是没力气头晕嘴唇发白是不是贫血"
  },
  {
    "id": 120,
    "tags": [
      "自主神经功能紊乱对多器官的影响"
    ],
    "confusion": "总觉得自己有病但检查正常是怎么回事"
  },
  {
    "id": 121,
    "tags": [
      "极度恐惧时交感神经激活与肾上腺素释放"
    ],
    "confusion": "恐高的人蹦极会不会猝死"
  },
  {
    "id": 122,
    "tags": [
      "过度换气导致血液碱中毒与低钙抽搐机制"
    ],
    "confusion": "情绪激动后四肢麻木抽搐是怎么回事"
  },
  {
    "id": 123,
    "tags": [
      "惊恐发作时交感神经过度激活机制",
      "肾上腺素释放引发心慌呼吸困难的生理过程"
    ],
    "confusion": "惊恐发作是怎么回事，为什么会突然心慌害怕"
  },
  {
    "id": 124,
    "tags": [
      "无需动画"
    ],
    "confusion": "想戒烟但不知道具体该怎么做"
  },
  {
    "id": 125,
    "tags": [
      "冠脉造影显示血管狭窄程度原理",
      "冠状动脉CT血管成像原理"
    ],
    "confusion": "想知道心脏血管堵不堵该做什么检查"
  },
  {
    "id": 126,
    "tags": [
      "病毒性心肌炎——病毒侵犯心肌细胞过程"
    ],
    "confusion": "感冒后心跳变快是不是心脏出问题了，是否需要吃药"
  },
  {
    "id": 127,
    "tags": [
      "慢性炎症因子损伤血管内皮过程",
      "低密度脂蛋白在受损内皮下沉积形成斑块"
    ],
    "confusion": "慢性炎症如何导致血管堵塞？"
  },
  {
    "id": 128,
    "tags": [
      "慢性病无症状期靶器官持续损害过程"
    ],
    "confusion": "慢性病没有症状是不是就不用治疗？"
  },
  {
    "id": 129,
    "tags": [
      "无需动画"
    ],
    "confusion": "慢性病管理为什么难以坚持？"
  },
  {
    "id": 130,
    "tags": [
      "胃黏膜从炎症到萎缩到肠化到癌变的演变"
    ],
    "confusion": "慢性胃炎会不会发展成胃癌"
  },
  {
    "id": 131,
    "tags": [
      "免疫球蛋白IgG与IgE介导的过敏反应机制差异"
    ],
    "confusion": "慢性食物过敏检测有必要做吗？会不会对常吃的食物隐性过敏？"
  },
  {
    "id": 132,
    "tags": [
      "心房颤动时心房电信号紊乱示意",
      "房扑时心房规则折返环路",
      "室上速时房室结折返传导"
    ],
    "confusion": "房颤、房扑、室上速同样是心慌，有什么区别？"
  },
  {
    "id": 133,
    "tags": [
      "心房颤动时心房电信号紊乱示意",
      "射频消融术消除异常传导灶过程"
    ],
    "confusion": "房颤一定要做手术吗？"
  },
  {
    "id": 134,
    "tags": [
      "心房颤动时心房电信号紊乱示意",
      "房颤时心房内血栓形成过程"
    ],
    "confusion": "房颤会有什么症状和感觉？"
  },
  {
    "id": 135,
    "tags": [
      "房颤时心房内血栓形成与脑栓塞",
      "阿司匹林抗血小板与华法林抗凝的机制差异"
    ],
    "confusion": "房颤患者吃阿司匹林能防脑梗吗？"
  },
  {
    "id": 136,
    "tags": [
      "心房颤动时心房电信号紊乱示意",
      "心室颤动导致心脏骤停机制"
    ],
    "confusion": "房颤是什么？房颤和室颤有什么区别？"
  },
  {
    "id": 137,
    "tags": [
      "心房颤动时心房电信号紊乱示意",
      "射频消融术消除异常传导灶过程"
    ],
    "confusion": "房颤是否必须做射频消融手术"
  },
  {
    "id": 138,
    "tags": [
      "结核杆菌感染与免疫应答过程",
      "卡介苗激活免疫系统的机制"
    ],
    "confusion": "打了卡介苗为什么还会得结核病？"
  },
  {
    "id": 139,
    "tags": [
      "抑郁症时大脑神经递质失衡示意"
    ],
    "confusion": "抑郁症和普通的懒惰消沉有什么区别"
  },
  {
    "id": 140,
    "tags": [
      "抗原抗体结合与免疫层析检测原理"
    ],
    "confusion": "抗原检测颜色深浅和病情严重程度有关吗？"
  },
  {
    "id": 141,
    "tags": [
      "肝脏合成与代谢胆固醇的过程"
    ],
    "confusion": "护肝片真的有用吗，指甲竖纹是肝不好吗"
  },
  {
    "id": 142,
    "tags": [
      "运动时心脏泵血增加与冠脉扩张"
    ],
    "confusion": "挥拍运动真的是对心脏最好的运动吗"
  },
  {
    "id": 143,
    "tags": [
      "支架内再狭窄与内皮化过程",
      "药物洗脱支架药物释放机制"
    ],
    "confusion": "支架术后怎么做才能不再狭窄？"
  },
  {
    "id": 144,
    "tags": [
      "冠脉支架撑开狭窄但不影响其他部位斑块破裂",
      "冠状动脉内斑块从稳定到破裂的过程"
    ],
    "confusion": "支架能不能预防心肌梗死"
  },
  {
    "id": 145,
    "tags": [
      "胰岛素与细胞表面受体结合调节血糖过程",
      "胰岛素抵抗时细胞对胰岛素反应减弱"
    ],
    "confusion": "改善胰岛素抵抗需要怎么控制饮食？水果和加餐算零食吗？"
  },
  {
    "id": 146,
    "tags": [
      "无需动画"
    ],
    "confusion": "放血疗法有没有科学依据"
  },
  {
    "id": 147,
    "tags": [
      "核磁共振成像原理与金属支架的磁场相互作用"
    ],
    "confusion": "放过心脏支架还能做核磁共振吗？"
  },
  {
    "id": 148,
    "tags": [
      "冠状动脉内斑块破裂与血栓脱落过程",
      "栓子随血流到达远端血管造成栓塞"
    ],
    "confusion": "斑块会不会掉下来引起心梗脑梗？"
  },
  {
    "id": 149,
    "tags": [
      "动脉粥样硬化斑块的结构组成",
      "血栓在血管内形成的凝血级联反应"
    ],
    "confusion": "斑块和血栓有什么区别？"
  },
  {
    "id": 150,
    "tags": [
      "动脉粥样硬化从脂纹到纤维斑块到易损斑块的演变"
    ],
    "confusion": "斑块是怎么演变的"
  },
  {
    "id": 1,
    "tags": [
      "人体代谢与能量消耗机制",
      "胰岛素分泌与血糖调节过程"
    ],
    "confusion": "断食减肥（如16+8）到底科不科学？"
  },
  {
    "id": 2,
    "tags": [
      "新冠病毒侵犯肺组织过程",
      "肺部CT影像变化示意"
    ],
    "confusion": "新冠住院患者的真实情况是什么样的？"
  },
  {
    "id": 3,
    "tags": [
      "新冠病毒对多器官损伤机制"
    ],
    "confusion": "新冠后常见后遗症有哪些，怎么应对"
  },
  {
    "id": 4,
    "tags": [
      "病毒侵犯心肌细胞过程",
      "心肌炎心肌损伤病理示意"
    ],
    "confusion": "新冠后怎么判断自己是不是心肌炎？"
  },
  {
    "id": 5,
    "tags": [
      "肺磨玻璃结节CT影像示意",
      "肺泡组织病变过程"
    ],
    "confusion": "新冠后查出肺磨玻璃结节严不严重"
  },
  {
    "id": 6,
    "tags": [
      "无需动画"
    ],
    "confusion": "新冠康复后什么时候可以运动？怎么运动才安全？"
  },
  {
    "id": 7,
    "tags": [
      "无需动画"
    ],
    "confusion": "新冠期间家里应该备哪些药？"
  },
  {
    "id": 8,
    "tags": [
      "抗病毒药物作用机制"
    ],
    "confusion": "新冠特效药需不需要囤"
  },
  {
    "id": 9,
    "tags": [
      "新冠病毒入侵细胞全过程",
      "病毒与ACE2受体结合机制",
      "免疫系统识别与攻击病毒过程"
    ],
    "confusion": "新冠病毒进入人体后发生了什么"
  },
  {
    "id": 10,
    "tags": [
      "无需动画"
    ],
    "confusion": "新冠转阴后饮食和生活上要注意什么？"
  },
  {
    "id": 11,
    "tags": [
      "新冠重症肺部病变过程",
      "体外膜肺氧合(ECMO)工作原理"
    ],
    "confusion": "新冠重症有哪些有效的治疗方法？"
  },
  {
    "id": 12,
    "tags": [
      "退烧药作用机制",
      "药物在肝脏代谢过程"
    ],
    "confusion": "新冠阳了之后怎么正确服药？退烧药能叠加吃吗？"
  },
  {
    "id": 13,
    "tags": [
      "骨髓造血与血细胞生成过程",
      "人体血液循环系统示意"
    ],
    "confusion": "无偿献血对身体有没有好处"
  },
  {
    "id": 14,
    "tags": [
      "免疫系统识别与攻击病毒过程",
      "病毒在体内复制但被免疫抑制示意"
    ],
    "confusion": "无症状感染到底是什么意思？"
  },
  {
    "id": 15,
    "tags": [
      "药物对血管收缩/舒张的影响机制",
      "肾脏水钠调节与血压关系"
    ],
    "confusion": "日常吃的药会不会反而引起高血压？"
  },
  {
    "id": 16,
    "tags": [
      "肾脏水钠调节与血压关系"
    ],
    "confusion": "日常喝水有哪些常见误区？"
  },
  {
    "id": 17,
    "tags": [
      "心脏电传导系统示意",
      "早搏时心脏电信号异常过程",
      "室颤与心脏骤停机制"
    ],
    "confusion": "早搏会引起猝死吗"
  },
  {
    "id": 18,
    "tags": [
      "血管随温度舒张收缩变化示意"
    ],
    "confusion": "春天血压变低了，降压药能不能减量或停药？"
  },
  {
    "id": 19,
    "tags": [
      "心脑血管急性事件发生机制"
    ],
    "confusion": "春节期间哪些急症高发，如何预防"
  },
  {
    "id": 20,
    "tags": [
      "无需动画"
    ],
    "confusion": "春节返乡后出现新冠症状怎么处理？"
  },
  {
    "id": 21,
    "tags": [
      "冠状动脉内斑块形成与破裂过程",
      "心脏骤停与室颤机制"
    ],
    "confusion": "普通人如何预防心梗和猝死"
  },
  {
    "id": 22,
    "tags": [
      "正常细胞癌变过程",
      "免疫系统监视与清除癌细胞机制"
    ],
    "confusion": "普通人怎么预防癌症？"
  },
  {
    "id": 23,
    "tags": [
      "光电传感器检测心率原理"
    ],
    "confusion": "智能手表的健康监测数据异常，需要担心吗？"
  },
  {
    "id": 24,
    "tags": [
      "卵巢功能衰退与激素水平变化过程"
    ],
    "confusion": "更年期有哪些典型症状，怎么应对"
  },
  {
    "id": 25,
    "tags": [
      "卵巢功能衰退与激素水平变化过程",
      "自主神经调节心脏功能示意"
    ],
    "confusion": "更年期症状会不会被误诊为心脏病"
  },
  {
    "id": 26,
    "tags": [
      "维生素在人体内的吸收与代谢过程"
    ],
    "confusion": "最容易缺乏的维生素是哪些？该怎么补？"
  },
  {
    "id": 27,
    "tags": [
      "颈动脉斑块形成过程",
      "斑块脱落导致脑梗机制",
      "冠状动脉内斑块形成与破裂过程"
    ],
    "confusion": "有了颈动脉斑块是不是离心梗脑梗不远了"
  },
  {
    "id": 28,
    "tags": [
      "无需动画"
    ],
    "confusion": "有人抽烟喝酒还长寿，是不是说明这些不影响健康？"
  },
  {
    "id": 29,
    "tags": [
      "药物在肝脏代谢过程"
    ],
    "confusion": "有哪些常见的用药误区"
  },
  {
    "id": 30,
    "tags": [
      "降压药对血管作用机制"
    ],
    "confusion": "有没有副作用小又效果好的降压药？"
  },
  {
    "id": 31,
    "tags": [
      "抗原检测试剂工作原理",
      "病毒在体内复制但被免疫抑制示意"
    ],
    "confusion": "有症状但抗原阴性，到底阳没阳？怎么保护家人？"
  },
  {
    "id": 32,
    "tags": [
      "肝脏细胞损伤与转氨酶释放过程"
    ],
    "confusion": "有箭头是不是就代表肝有问题"
  },
  {
    "id": 33,
    "tags": [
      "颈动脉斑块形成过程",
      "斑块脱落导致脑梗机制",
      "颈动脉内膜剥脱术/支架手术示意"
    ],
    "confusion": "查出颈动脉斑块是不是快脑梗了，要不要吃药/手术？"
  },
  {
    "id": 34,
    "tags": [
      "他汀类药物稳定斑块机制",
      "颈动脉斑块形成过程"
    ],
    "confusion": "查出颈动脉斑块要不要吃他汀？"
  },
  {
    "id": 35,
    "tags": [
      "食物消化吸收后血脂变化过程"
    ],
    "confusion": "查血脂为什么必须空腹？"
  },
  {
    "id": 36,
    "tags": [
      "自主神经功能紊乱对身体的影响示意"
    ],
    "confusion": "检查都正常但身体总不舒服，是不是焦虑？"
  },
  {
    "id": 37,
    "tags": [
      "Omega-6脂肪酸代谢与炎症反应通路"
    ],
    "confusion": "植物油里的Omega-6会导致慢性炎症吗？"
  },
  {
    "id": 38,
    "tags": [
      "自主神经(交感/副交感)调节机制"
    ],
    "confusion": "植物神经功能紊乱是怎么得的"
  },
  {
    "id": 39,
    "tags": [
      "维生素在人体内的吸收与代谢过程"
    ],
    "confusion": "正常吃饭会不会缺维生素"
  },
  {
    "id": 40,
    "tags": [
      "无需动画"
    ],
    "confusion": "每周150分钟运动应该怎么分配到每天"
  },
  {
    "id": 41,
    "tags": [
      "酒精对心肌细胞和血管的影响机制"
    ],
    "confusion": "每天少量喝酒真的对心脏有好处吗"
  },
  {
    "id": 42,
    "tags": [
      "咽喉与气管黏膜分泌痰液过程",
      "胃食管反流刺激咽喉示意"
    ],
    "confusion": "每天早起嗓子有痰咳不出来是什么原因"
  },
  {
    "id": 43,
    "tags": [
      "无需动画"
    ],
    "confusion": "每天走多少步最合适"
  },
  {
    "id": 44,
    "tags": [
      "关节软骨磨损过程",
      "心脏在不同运动强度下负荷变化"
    ],
    "confusion": "每天跑步十公里是不是健康的运动方式"
  },
  {
    "id": 45,
    "tags": [
      "果糖在肝脏代谢转化为脂肪过程"
    ],
    "confusion": "水果里的果糖是否对身体有害、要不要少吃水果"
  },
  {
    "id": 46,
    "tags": [
      "骨质疏松骨微结构退化过程",
      "骨骼内部正常与疏松对比示意"
    ],
    "confusion": "没有外伤骨头也会断吗？自发性骨折是怎么回事？"
  },
  {
    "id": 47,
    "tags": [
      "无症状疾病在体内隐匿进展示意"
    ],
    "confusion": "没有症状是不是就没有病"
  },
  {
    "id": 48,
    "tags": [
      "无需动画"
    ],
    "confusion": "没有箭头是不是就没问题？"
  },
  {
    "id": 49,
    "tags": [
      "动脉粥样硬化形成过程",
      "冠状动脉内斑块形成与破裂过程"
    ],
    "confusion": "没有高血压糖尿病为什么也会得心脏病或血管堵塞"
  },
  {
    "id": 50,
    "tags": [
      "牙结石形成与牙龈退缩过程",
      "超声波洁牙工作原理"
    ],
    "confusion": "洗牙到底好不好，会不会伤牙"
  },
  {
    "id": 51,
    "tags": [
      "慢阻肺肺泡损伤与气流受限示意",
      "心功能不全导致肺淤血机制"
    ],
    "confusion": "活动后气喘是心脏病还是肺病（慢阻肺）"
  },
  {
    "id": 52,
    "tags": [
      "冠状动脉供血不足与心肌缺血过程"
    ],
    "confusion": "活动后胸口隐隐不适算不算心脏问题"
  },
  {
    "id": 53,
    "tags": [
      "心脏电传导系统示意",
      "运动时心脏自主神经调节机制"
    ],
    "confusion": "活动时心慌是什么原因，怎么诊断"
  },
  {
    "id": 54,
    "tags": [
      "冠状动脉供血不足与心肌缺血过程",
      "运动时冠脉血流需求增加示意"
    ],
    "confusion": "活动时胸痛休息时正常是不是心脏病"
  },
  {
    "id": 55,
    "tags": [
      "纳米机器人在血管内溶栓概念示意",
      "血栓形成与溶解过程"
    ],
    "confusion": "溶栓纳米机器人是真的吗？"
  },
  {
    "id": 56,
    "tags": [
      "真菌侵入甲板结构过程"
    ],
    "confusion": "灰指甲怎么治？"
  },
  {
    "id": 57,
    "tags": [
      "炎症反应全过程(免疫细胞聚集/血管扩张)",
      "慢性炎症对组织的持续损伤示意"
    ],
    "confusion": "炎症是不是身体的毒药？"
  },
  {
    "id": 58,
    "tags": [
      "高温导致体温调节系统衰竭过程",
      "热射病时器官损伤机制"
    ],
    "confusion": "热射病为什么会致死，高温对人体有多危险"
  },
  {
    "id": 59,
    "tags": [
      "无需动画"
    ],
    "confusion": "牛奶到底会不会致癌"
  },
  {
    "id": 60,
    "tags": [
      "无需动画"
    ],
    "confusion": "牛奶性寒/有激素/致炎，到底能不能喝？"
  },
  {
    "id": 61,
    "tags": [
      "牛磺酸在细胞内的代谢作用示意"
    ],
    "confusion": "牛磺酸真的有降血脂、降血糖、增肌等多种功效吗？"
  },
  {
    "id": 62,
    "tags": [
      "人体散热与体温调节机制"
    ],
    "confusion": "物理降温的正确方法是什么？退热贴贴额头有用吗？"
  },
  {
    "id": 63,
    "tags": [
      "甲状腺激素调节代谢过程",
      "消化道营养吸收机制"
    ],
    "confusion": "特别瘦怎么吃都不胖，是不是有病？"
  },
  {
    "id": 64,
    "tags": [
      "心梗时冠状动脉血栓堵塞过程",
      "心肺复苏(CPR)操作原理示意"
    ],
    "confusion": "独居时突发心梗，应该优先做哪些急救操作？"
  },
  {
    "id": 65,
    "tags": [
      "心脏骤停与室颤机制",
      "心脏电传导系统示意",
      "冠状动脉内斑块形成与破裂过程"
    ],
    "confusion": "猝死前一分钟心脏发生了什么变化"
  },
  {
    "id": 66,
    "tags": [
      "剧烈运动时心脏负荷变化示意",
      "心脏骤停与室颤机制"
    ],
    "confusion": "猝死是不是因为运动过量导致的"
  },
  {
    "id": 67,
    "tags": [
      "饱和脂肪酸对血管内壁影响示意"
    ],
    "confusion": "猪油是不是不健康，还能不能吃"
  },
  {
    "id": 68,
    "tags": [
      "甘油三酯沉积导致动脉粥样硬化过程",
      "高甘油三酯引发急性胰腺炎机制"
    ],
    "confusion": "甘油三酯高有什么危害？"
  },
  {
    "id": 69,
    "tags": [
      "肝脏细胞损伤与转氨酶释放过程",
      "肾小球滤过机制"
    ],
    "confusion": "生化（肝肾功能）化验单怎么看"
  },
  {
    "id": 70,
    "tags": [
      "情绪激动时交感神经激活与血管收缩过程",
      "应激激素对心血管系统影响机制"
    ],
    "confusion": "生气是否真的会导致心脏病和血管损伤"
  },
  {
    "id": 71,
    "tags": [
      "致癌物导致DNA损伤与细胞突变过程"
    ],
    "confusion": "生活中常见的致癌物有哪些？"
  },
  {
    "id": 72,
    "tags": [
      "人体电解质平衡调节机制"
    ],
    "confusion": "生病发烧时应该喝电解质水还是白开水？"
  },
  {
    "id": 73,
    "tags": [
      "用力屏气时胸腔压力变化与冠脉血流影响",
      "冠状动脉内斑块形成与破裂过程"
    ],
    "confusion": "用力排便会不会诱发心梗？"
  },
  {
    "id": 74,
    "tags": [
      "甲型流感病毒入侵呼吸道上皮细胞过程",
      "免疫系统识别与攻击病毒过程"
    ],
    "confusion": "甲流为什么突然这么多，怎么防"
  },
  {
    "id": 75,
    "tags": [
      "甲状腺结节压迫/破坏甲状腺组织示意",
      "甲状腺激素分泌调节机制"
    ],
    "confusion": "甲状腺结节会不会导致甲减"
  },
  {
    "id": 76,
    "tags": [
      "甲状腺结节良性与恶性病变对比示意",
      "正常细胞癌变过程"
    ],
    "confusion": "甲状腺结节会不会癌变？"
  },
  {
    "id": 77,
    "tags": [
      "病毒与宿主共进化示意"
    ],
    "confusion": "病毒全消灭了世界会更好吗"
  },
  {
    "id": 78,
    "tags": [
      "噬菌体攻击细菌过程",
      "病毒基因与人类基因组整合示意"
    ],
    "confusion": "病毒对人类有没有好处"
  },
  {
    "id": 79,
    "tags": [
      "尿酸结晶在关节沉积过程",
      "嘌呤代谢与尿酸生成通路"
    ],
    "confusion": "痛风患者到底能吃什么不能吃什么"
  },
  {
    "id": 80,
    "tags": [
      "尿酸结晶在关节沉积过程",
      "嘌呤代谢与尿酸生成通路"
    ],
    "confusion": "痛风是什么、怎么识别？"
  },
  {
    "id": 81,
    "tags": [
      "内脏脂肪在肝细胞内堆积过程"
    ],
    "confusion": "瘦人为什么也会得脂肪肝"
  },
  {
    "id": 82,
    "tags": [
      "肝脏合成与代谢血脂过程",
      "低密度脂蛋白在血管内沉积示意"
    ],
    "confusion": "瘦的人为什么也会血脂高？"
  },
  {
    "id": 83,
    "tags": [
      "正常细胞癌变过程",
      "基因突变与遗传易感性示意"
    ],
    "confusion": "癌症到底是遗传还是饮食导致的，该怎么看待健康风险"
  },
  {
    "id": 84,
    "tags": [
      "正常细胞癌变过程",
      "DNA损伤与修复失败机制",
      "肿瘤血管新生与转移过程"
    ],
    "confusion": "癌症是怎么发生的，正常细胞怎么变成癌细胞"
  },
  {
    "id": 85,
    "tags": [
      "癌细胞能量代谢(瓦博格效应)示意"
    ],
    "confusion": "癌细胞是不是只靠糖供能"
  },
  {
    "id": 86,
    "tags": [
      "无需动画"
    ],
    "confusion": "看不起病是不是健康最大的障碍"
  },
  {
    "id": 87,
    "tags": [
      "无需动画"
    ],
    "confusion": "看病不知道该挂什么科？"
  },
  {
    "id": 88,
    "tags": [
      "无需动画"
    ],
    "confusion": "看病时如何与医生有效沟通"
  },
  {
    "id": 89,
    "tags": [
      "睡眠呼吸暂停时上气道塌陷过程",
      "睡眠周期与脑电波变化示意"
    ],
    "confusion": "睡觉多梦、睡醒没精神，是不是睡眠呼吸暂停？"
  },
  {
    "id": 90,
    "tags": [
      "睡眠周期与脑电波变化示意"
    ],
    "confusion": "睡觉总做梦、醒来没精神是怎么回事"
  },
  {
    "id": 91,
    "tags": [
      "硝酸甘油扩张血管机制",
      "眼内房水循环与眼压调节示意"
    ],
    "confusion": "硝酸甘油等扩血管药会不会引发青光眼"
  },
  {
    "id": 92,
    "tags": [
      "心脏电传导系统示意",
      "运动时心脏自主神经调节机制"
    ],
    "confusion": "稍微活动心率就很快是不是心脏有问题"
  },
  {
    "id": 93,
    "tags": [
      "胰岛素分泌与血糖调节过程",
      "胰岛β细胞功能下降示意"
    ],
    "confusion": "空腹血糖大于5.6是不是就算糖尿病前期"
  },
  {
    "id": 94,
    "tags": [
      "内耳前庭系统平衡调节机制",
      "脑部供血不足示意"
    ],
    "confusion": "突发头晕可能是什么原因，该怎么处理"
  },
  {
    "id": 95,
    "tags": [
      "心梗时冠状动脉血栓堵塞过程",
      "心肺复苏(CPR)操作原理示意"
    ],
    "confusion": "突发心梗如何自救或救家人？"
  },
  {
    "id": 96,
    "tags": [
      "恶性肿瘤消耗机体营养机制",
      "甲状腺激素调节代谢过程"
    ],
    "confusion": "突然变瘦是好事吗？可能是什么严重疾病？"
  },
  {
    "id": 97,
    "tags": [
      "心脏电传导系统示意",
      "窦房结节律产生与传导过程"
    ],
    "confusion": "窦性心律不齐需不需要治疗、会不会损伤心脏"
  },
  {
    "id": 98,
    "tags": [
      "无需动画"
    ],
    "confusion": "站桩算不算有效运动？"
  },
  {
    "id": 99,
    "tags": [
      "糖类摄入后大脑多巴胺奖赏通路激活",
      "胰岛素分泌与血糖调节过程"
    ],
    "confusion": "糖为什么会上瘾，过量摄入有什么危害"
  },
  {
    "id": 100,
    "tags": [
      "血红蛋白与葡萄糖结合(糖化)过程"
    ],
    "confusion": "糖化血红蛋白是什么、有什么用"
  },
  {
    "id": 101,
    "tags": [
      "胰岛素分泌与血糖调节过程",
      "不同降糖药作用靶点对比示意"
    ],
    "confusion": "糖尿病为什么不同人用药不一样？"
  },
  {
    "id": 102,
    "tags": [
      "胰岛β细胞功能下降示意",
      "胰岛素抵抗机制"
    ],
    "confusion": "糖尿病主要是基因还是生活方式导致的"
  },
  {
    "id": 103,
    "tags": [
      "食物消化后血糖升高曲线示意",
      "胰岛素分泌与血糖调节过程"
    ],
    "confusion": "糖尿病前期（血糖刚升高）应该怎么吃"
  },
  {
    "id": 104,
    "tags": [
      "高血糖损伤血管内皮过程",
      "糖尿病微血管病变机制"
    ],
    "confusion": "糖尿病对血管有什么影响？"
  },
  {
    "id": 105,
    "tags": [
      "糖尿病多器官并发症全景示意"
    ],
    "confusion": "糖尿病患者日常要注意什么？"
  },
  {
    "id": 106,
    "tags": [
      "低密度脂蛋白在血管内沉积示意"
    ],
    "confusion": "糖尿病患者的血脂报告该怎么看"
  },
  {
    "id": 107,
    "tags": [
      "果糖在肝脏代谢转化为脂肪过程",
      "胰岛素分泌与血糖调节过程"
    ],
    "confusion": "糖尿病或胰岛素抵抗的人怎么吃水果"
  },
  {
    "id": 108,
    "tags": [
      "血红蛋白与葡萄糖结合(糖化)过程",
      "糖尿病微血管病变机制"
    ],
    "confusion": "糖尿病控制得好不好看什么指标"
  },
  {
    "id": 109,
    "tags": [
      "胰岛β细胞功能下降示意",
      "胰岛素抵抗机制"
    ],
    "confusion": "糖尿病早期有哪些征兆"
  },
  {
    "id": 110,
    "tags": [
      "胰岛素分泌与血糖调节过程",
      "高血糖损伤血管内皮过程",
      "糖尿病多器官并发症全景示意"
    ],
    "confusion": "糖尿病是怎么回事、为什么会导致那么多并发症"
  },
  {
    "id": 111,
    "tags": [
      "胰岛β细胞功能下降示意",
      "胰岛素分泌与血糖调节过程"
    ],
    "confusion": "糖尿病能逆转吗，是不是一辈子要吃药"
  },
  {
    "id": 112,
    "tags": [
      "糖类摄入后大脑多巴胺奖赏通路激活"
    ],
    "confusion": "糖瘾是怎么回事"
  },
  {
    "id": 113,
    "tags": [
      "头颈部肌肉紧张与疼痛传导示意"
    ],
    "confusion": "紧张性头痛怎么缓解"
  },
  {
    "id": 114,
    "tags": [
      "致癌物导致DNA损伤与细胞突变过程"
    ],
    "confusion": "红肉是致癌物，还能不能吃？"
  },
  {
    "id": 115,
    "tags": [
      "胃食管反流(贲门松弛/胃酸倒流)机制",
      "食管黏膜被胃酸腐蚀过程"
    ],
    "confusion": "经常反酸烧心是怎么回事，胃食管反流有什么危害"
  },
  {
    "id": 116,
    "tags": [
      "胰岛素分泌与血糖调节过程",
      "血糖波动曲线(反应性低血糖)示意"
    ],
    "confusion": "经常容易饿和低血糖是怎么回事"
  },
  {
    "id": 117,
    "tags": [
      "心脏电传导系统示意",
      "运动时心脏自主神经调节机制"
    ],
    "confusion": "经常心慌、心跳快是心脏病吗？"
  },
  {
    "id": 118,
    "tags": [
      "肠道菌群与气体产生过程",
      "结肠息肉与癌变过程"
    ],
    "confusion": "经常放屁是不是肠癌的表现"
  },
  {
    "id": 119,
    "tags": [
      "免疫系统识别与攻击病毒过程"
    ],
    "confusion": "经常生病是免疫力低下吗"
  },
  {
    "id": 120,
    "tags": [
      "结肠息肉与癌变过程",
      "肠镜下息肉切除示意"
    ],
    "confusion": "结肠癌能预防吗，怎么预防"
  },
  {
    "id": 121,
    "tags": [
      "维生素C在人体内的吸收与代谢过程"
    ],
    "confusion": "维生素C需不需要额外补充？"
  },
  {
    "id": 122,
    "tags": [
      "维生素在人体内的吸收与代谢过程",
      "脂溶性维生素在肝脏蓄积示意"
    ],
    "confusion": "维生素能不能长期随便补"
  },
  {
    "id": 123,
    "tags": [
      "缓释片药物释放机制剖面示意"
    ],
    "confusion": "缓释片能不能掰开吃"
  },
  {
    "id": 124,
    "tags": [
      "缺血预适应时组织耐受机制",
      "冠状动脉侧支循环建立过程"
    ],
    "confusion": "缺血预适应训练真的能预防心梗脑梗吗"
  },
  {
    "id": 125,
    "tags": [
      "阿尔茨海默病脑内β淀粉样蛋白沉积过程",
      "正常大脑与萎缩大脑对比示意"
    ],
    "confusion": "老人性格大变、爱忘事是正常衰老还是老年痴呆？"
  },
  {
    "id": 126,
    "tags": [
      "心脏电传导系统示意",
      "窦房结节律产生与传导过程"
    ],
    "confusion": "老年人心率80-90正常吗"
  },
  {
    "id": 127,
    "tags": [
      "肌肉流失(肌少症)过程示意"
    ],
    "confusion": "老年人越瘦越好吗"
  },
  {
    "id": 128,
    "tags": [
      "阿尔茨海默病脑内β淀粉样蛋白沉积过程",
      "正常大脑与萎缩大脑对比示意"
    ],
    "confusion": "老年痴呆的早期症状有哪些？"
  },
  {
    "id": 129,
    "tags": [
      "冠状动脉内斑块形成与破裂过程"
    ],
    "confusion": "耳垂有折痕是不是心脏病的预兆"
  },
  {
    "id": 130,
    "tags": [
      "内耳耳蜗毛细胞损伤与信号传导异常",
      "听觉神经通路示意"
    ],
    "confusion": "耳鸣是怎么产生的、该如何缓解"
  },
  {
    "id": 131,
    "tags": [
      "内耳耳蜗毛细胞损伤与信号传导异常",
      "听觉神经通路示意"
    ],
    "confusion": "耳鸣是怎么回事，怎么消除"
  },
  {
    "id": 132,
    "tags": [
      "肾小球滤过机制",
      "肾功能下降与肌酐清除率变化示意"
    ],
    "confusion": "肌酐升高意味着什么"
  },
  {
    "id": 133,
    "tags": [
      "肾小球滤过机制",
      "肾功能代偿与失代偿过程"
    ],
    "confusion": "肌酐没有箭头是否就代表肾没问题"
  },
  {
    "id": 134,
    "tags": [
      "腹部脏器分布与对应疼痛区域示意"
    ],
    "confusion": "肚子不同位置的疼痛分别是什么原因"
  },
  {
    "id": 135,
    "tags": [
      "他汀类药物在肝脏的代谢过程",
      "肝脏细胞损伤与转氨酶释放过程"
    ],
    "confusion": "肝功能不好的人能不能吃他汀"
  },
  {
    "id": 136,
    "tags": [
      "肝脏细胞损伤与转氨酶释放过程"
    ],
    "confusion": "肝功能化验单上那么多指标该怎么看"
  },
  {
    "id": 137,
    "tags": [
      "肝脏从脂肪肝到肝硬化到肝癌逐步病变过程"
    ],
    "confusion": "肝脏是怎么一步步走向肝硬化和肝癌的"
  },
  {
    "id": 138,
    "tags": [
      "肝脏内部结构与代偿功能示意",
      "肝脏从脂肪肝到肝硬化到肝癌逐步病变过程"
    ],
    "confusion": "肝脏疾病为什么没有早期症状？"
  },
  {
    "id": 139,
    "tags": [
      "肠道神经系统(脑-肠轴)信号传导示意"
    ],
    "confusion": "肠易激综合征和精神压力有关吗"
  },
  {
    "id": 140,
    "tags": [
      "肥厚性心肌病心室壁增厚示意",
      "心脏流出道梗阻机制",
      "心脏骤停与室颤机制"
    ],
    "confusion": "肥厚性心肌病是什么，为什么会导致年轻人猝死"
  },
  {
    "id": 141,
    "tags": [
      "深静脉血栓脱落经血流至肺动脉过程",
      "肺动脉栓塞导致气体交换受阻示意"
    ],
    "confusion": "肺栓塞是什么"
  },
  {
    "id": 142,
    "tags": [
      "肺结节从良性到恶性演变过程",
      "肺泡组织病变过程"
    ],
    "confusion": "肺结节有多少会变成肺癌？需要多久？"
  },
  {
    "id": 143,
    "tags": [
      "肾小球滤过机制",
      "高血压/糖尿病对肾小球损伤过程"
    ],
    "confusion": "肾功能为什么会受损"
  },
  {
    "id": 144,
    "tags": [
      "肾结石在肾脏/输尿管内形成过程",
      "尿液中矿物质结晶沉积示意"
    ],
    "confusion": "肾结石是怎么形成的"
  },
  {
    "id": 145,
    "tags": [
      "肾小球滤过机制",
      "肾单位逐步损毁到肾衰竭全过程"
    ],
    "confusion": "肾脏是怎么一步步走向肾衰竭/尿毒症的？"
  },
  {
    "id": 146,
    "tags": [
      "免疫检查点抑制剂解除肿瘤免疫逃逸机制",
      "T细胞识别与攻击肿瘤细胞过程"
    ],
    "confusion": "肿瘤免疫疗法的原理是什么"
  },
  {
    "id": 147,
    "tags": [
      "正常细胞癌变过程",
      "肿瘤血管新生与转移过程"
    ],
    "confusion": "肿瘤有哪些早期迹象"
  },
  {
    "id": 148,
    "tags": [
      "肿瘤标志物从肿瘤细胞释放入血过程"
    ],
    "confusion": "肿瘤标志物升高是不是就是得了癌症？"
  },
  {
    "id": 149,
    "tags": [
      "免疫系统监视与清除癌细胞机制"
    ],
    "confusion": "肿瘤能自愈吗"
  },
  {
    "id": 150,
    "tags": [
      "胃食管反流(贲门松弛/胃酸倒流)机制",
      "食管与心脏解剖位置毗邻关系示意"
    ],
    "confusion": "胃食管反流会不会被误诊为心脏问题"
  },
  {
    "id": 1,
    "tags": [
      "胃食管反流发生机制（贲门松弛与胃酸逆流）",
      "膈肌与腹压对食管下括约肌的影响"
    ],
    "confusion": "胃食管反流怎么通过锻炼缓解"
  },
  {
    "id": 2,
    "tags": [
      "胆固醇在细胞膜中的结构功能",
      "低密度脂蛋白在血管壁沉积过程"
    ],
    "confusion": "胆固醇到底是好东西还是坏东西"
  },
  {
    "id": 3,
    "tags": [
      "胆固醇在细胞膜中的结构功能",
      "低密度脂蛋白在血管壁沉积过程"
    ],
    "confusion": "胆固醇是人体必需的所以不用降吗？"
  },
  {
    "id": 4,
    "tags": [
      "胆固醇在细胞膜中的结构功能",
      "低密度脂蛋白在血管壁沉积过程",
      "高密度脂蛋白逆向转运胆固醇过程"
    ],
    "confusion": "胆固醇是好是坏？关于胆固醇的常见疑问"
  },
  {
    "id": 5,
    "tags": [
      "他汀类药物抑制肝脏胆固醇合成机制",
      "低密度脂蛋白在血管壁沉积过程"
    ],
    "confusion": "胆固醇高了是不是就要吃他汀"
  },
  {
    "id": 6,
    "tags": [
      "冠状动脉内斑块形成与狭窄进展过程",
      "低密度脂蛋白在血管壁沉积过程"
    ],
    "confusion": "胆固醇高到什么程度会得冠心病"
  },
  {
    "id": 7,
    "tags": [
      "胰岛素与细胞受体结合及信号传导过程",
      "胰岛素抵抗时脂肪组织代谢紊乱示意",
      "内脏脂肪堆积与代谢综合征关联示意"
    ],
    "confusion": "胰岛素抵抗为什么会导致肥胖和代谢综合征"
  },
  {
    "id": 8,
    "tags": [
      "胰岛素抵抗时脂肪组织代谢紊乱示意",
      "胰岛素抵抗导致血糖血脂血压升高的病理通路"
    ],
    "confusion": "胰岛素抵抗和三高有什么关系？"
  },
  {
    "id": 9,
    "tags": [
      "胰岛素与细胞受体结合及信号传导过程",
      "胰岛素敏感性恢复过程示意"
    ],
    "confusion": "胰岛素抵抗怎么逆转/改善？"
  },
  {
    "id": 10,
    "tags": [
      "胰岛素与细胞受体结合及信号传导过程",
      "胰岛素抵抗时细胞对胰岛素反应减弱示意"
    ],
    "confusion": "胰岛素抵抗是什么"
  },
  {
    "id": 11,
    "tags": [
      "胰岛素抵抗时细胞对胰岛素反应减弱示意",
      "内脏脂肪堆积与代谢综合征关联示意"
    ],
    "confusion": "胰岛素抵抗是怎么形成的"
  },
  {
    "id": 12,
    "tags": [
      "心绞痛发作时冠状动脉供血不足示意",
      "胸痛鉴别诊断解剖示意（心脏、食管、肌肉骨骼）"
    ],
    "confusion": "胸口疼是不是心脏病？心绞痛到底是什么感觉？"
  },
  {
    "id": 13,
    "tags": [
      "胃食管反流发生机制（贲门松弛与胃酸逆流）",
      "胸痛鉴别诊断解剖示意（心脏、食管、肌肉骨骼）"
    ],
    "confusion": "胸口痛伴打嗝查不出原因是怎么回事"
  },
  {
    "id": 14,
    "tags": [
      "心绞痛发作时冠状动脉供血不足示意",
      "胸痛鉴别诊断解剖示意（心脏、食管、肌肉骨骼）"
    ],
    "confusion": "胸口闷或痛是不是心脏病"
  },
  {
    "id": 15,
    "tags": [
      "胸痛鉴别诊断解剖示意（心脏、食管、肌肉骨骼）",
      "肺栓塞发生过程示意",
      "气胸发生机制示意"
    ],
    "confusion": "胸痛一定是心脏病吗，还可能是什么病"
  },
  {
    "id": 16,
    "tags": [
      "心绞痛发作时冠状动脉供血不足示意",
      "胸痛鉴别诊断解剖示意（心脏、食管、肌肉骨骼）"
    ],
    "confusion": "胸痛是不是心脏病？心绞痛到底是什么感觉？"
  },
  {
    "id": 17,
    "tags": [
      "胸痛鉴别诊断解剖示意（心脏、食管、肌肉骨骼）",
      "急性心肌梗死发生过程",
      "主动脉夹层撕裂过程示意"
    ],
    "confusion": "胸痛是怎么回事，哪些胸痛危及生命"
  },
  {
    "id": 18,
    "tags": [
      "冠状动脉内斑块形成与狭窄进展过程",
      "激光消融术与冠脉支架植入对比示意"
    ],
    "confusion": "能不能用激光把斑块融掉从而不放支架"
  },
  {
    "id": 19,
    "tags": [
      "脂肪肝形成过程（肝细胞内脂肪沉积）",
      "脂肪肝向肝纤维化进展过程"
    ],
    "confusion": "脂肪肝严重吗要不要管"
  },
  {
    "id": 20,
    "tags": [
      "脂肪肝形成过程（肝细胞内脂肪沉积）",
      "他汀类药物抑制肝脏胆固醇合成机制"
    ],
    "confusion": "脂肪肝导致肝酶升高还能吃他汀吗"
  },
  {
    "id": 21,
    "tags": [
      "脂蛋白(a)结构及其在血管壁沉积过程"
    ],
    "confusion": "脂蛋白a高怎么办、能不能降下来"
  },
  {
    "id": 22,
    "tags": [
      "脑血管闭塞导致脑组织缺血过程",
      "脑卒中预警信号对应脑区功能示意"
    ],
    "confusion": "脑中风的危险信号有哪些"
  },
  {
    "id": 23,
    "tags": [
      "脑出血时血肿压迫脑组织过程",
      "颅内压升高与脑疝形成示意"
    ],
    "confusion": "脑出血为什么后果这么严重"
  },
  {
    "id": 24,
    "tags": [
      "脑出血时血肿压迫脑组织过程",
      "脑血管闭塞导致脑组织缺血过程"
    ],
    "confusion": "脑出血和脑梗死哪个更严重"
  },
  {
    "id": 25,
    "tags": [
      "脑出血时血肿压迫脑组织过程",
      "脑血管闭塞导致脑组织缺血过程"
    ],
    "confusion": "脑出血和脑梗死哪个更可怕"
  },
  {
    "id": 26,
    "tags": [
      "脑出血时血肿压迫脑组织过程",
      "脑内小动脉破裂机制"
    ],
    "confusion": "脑出血是怎么发生的、有多严重"
  },
  {
    "id": 27,
    "tags": [
      "脑出血时血肿压迫脑组织过程",
      "脑内小动脉破裂机制"
    ],
    "confusion": "脑出血是怎么回事"
  },
  {
    "id": 28,
    "tags": [
      "脑血管闭塞导致脑组织缺血过程",
      "脑出血时血肿压迫脑组织过程"
    ],
    "confusion": "脑卒中常见误解有哪些"
  },
  {
    "id": 29,
    "tags": [
      "脑血管闭塞导致脑组织缺血过程",
      "脑卒中预警信号对应脑区功能示意"
    ],
    "confusion": "脑梗发作前有哪些容易被忽视的信号？"
  },
  {
    "id": 30,
    "tags": [
      "脑血管闭塞导致脑组织缺血过程",
      "急性心肌梗死发生过程",
      "动脉粥样硬化斑块破裂与血栓形成"
    ],
    "confusion": "脑梗是怎么发生的？和心梗一样吗？"
  },
  {
    "id": 31,
    "tags": [
      "脑血管闭塞导致脑组织缺血过程",
      "动脉粥样硬化斑块破裂与血栓形成"
    ],
    "confusion": "脑梗死是怎么发生的"
  },
  {
    "id": 32,
    "tags": [
      "下肢动脉硬化闭塞导致足部缺血示意",
      "糖尿病足周围神经病变示意"
    ],
    "confusion": "脚凉就该泡脚吗"
  },
  {
    "id": 33,
    "tags": [
      "无需动画"
    ],
    "confusion": "脚气应该怎么正确治疗"
  },
  {
    "id": 34,
    "tags": [
      "下肢静脉回流障碍导致水肿机制",
      "心力衰竭导致下肢水肿机制"
    ],
    "confusion": "脚肿脚疼是什么病？"
  },
  {
    "id": 35,
    "tags": [
      "脑内小动脉闭塞形成腔隙性梗死灶示意"
    ],
    "confusion": "腔隙性脑梗死严重吗，需要吃药治疗吗"
  },
  {
    "id": 36,
    "tags": [
      "腰椎间盘突出压迫神经根过程",
      "椎间盘结构与退变示意"
    ],
    "confusion": "腰椎间盘突出是什么、为什么会引起腰痛"
  },
  {
    "id": 37,
    "tags": [
      "无需动画"
    ],
    "confusion": "腰痛应该做什么锻炼来缓解"
  },
  {
    "id": 38,
    "tags": [
      "骨质疏松骨微结构退化示意",
      "腰椎间盘突出压迫神经根过程"
    ],
    "confusion": "腰腿痛是骨质疏松引起的吗"
  },
  {
    "id": 39,
    "tags": [
      "下肢静脉瓣膜功能不全与静脉曲张形成过程"
    ],
    "confusion": "腿上出现静脉曲张怎么回事，需要治疗吗？"
  },
  {
    "id": 40,
    "tags": [
      "肌肉收缩时钙离子参与兴奋-收缩耦联过程"
    ],
    "confusion": "腿抽筋是不是就是缺钙"
  },
  {
    "id": 41,
    "tags": [
      "下肢静脉回流障碍导致水肿机制",
      "心力衰竭导致下肢水肿机制",
      "肾脏滤过功能异常导致水肿机制"
    ],
    "confusion": "腿肿一摁一个坑，是正常现象还是脏器出了问题？"
  },
  {
    "id": 42,
    "tags": [
      "无需动画"
    ],
    "confusion": "膝关节出问题该怎么看病、挂什么科？"
  },
  {
    "id": 43,
    "tags": [
      "膝关节软骨退化与骨性关节炎进展过程"
    ],
    "confusion": "膝关节炎是怎么回事？膝盖有问题怎么办？"
  },
  {
    "id": 44,
    "tags": [
      "膝关节软骨退化与骨性关节炎进展过程"
    ],
    "confusion": "膝关节疼痛除了吃药还能怎么缓解？"
  },
  {
    "id": 45,
    "tags": [
      "无需动画"
    ],
    "confusion": "膝盖不好或身体虚弱的人怎么锻炼？"
  },
  {
    "id": 46,
    "tags": [
      "膝关节软骨退化与骨性关节炎进展过程",
      "关节软骨在适度运动中的营养代谢示意"
    ],
    "confusion": "膝盖是用进废退还是越用越废、运动会不会伤膝盖"
  },
  {
    "id": 47,
    "tags": [
      "膝关节软骨退化与骨性关节炎进展过程",
      "关节软骨在适度运动中的营养代谢示意"
    ],
    "confusion": "膝盖疼光吃药不锻炼为什么好不了"
  },
  {
    "id": 48,
    "tags": [
      "无需动画"
    ],
    "confusion": "花生有什么健康价值？"
  },
  {
    "id": 49,
    "tags": [
      "无需动画"
    ],
    "confusion": "花钱多就能治好病吗"
  },
  {
    "id": 50,
    "tags": [
      "荔枝中次甲基环丙基甘氨酸抑制糖异生机制"
    ],
    "confusion": "荔枝吃多了为什么反而会降血糖"
  },
  {
    "id": 51,
    "tags": [
      "荔枝中次甲基环丙基甘氨酸抑制糖异生机制"
    ],
    "confusion": "荔枝病是什么，为什么吃荔枝会致病"
  },
  {
    "id": 52,
    "tags": [
      "无需动画"
    ],
    "confusion": "药物有副作用是不是就应该停药或换药"
  },
  {
    "id": 53,
    "tags": [
      "药物球囊扩张血管并释放药物过程",
      "冠脉支架植入与血管扩张过程"
    ],
    "confusion": "药物球囊和支架哪个更好？"
  },
  {
    "id": 54,
    "tags": [
      "无需动画"
    ],
    "confusion": "蜂蜜真的有营养和保健功效吗？"
  },
  {
    "id": 55,
    "tags": [
      "血压形成原理（心脏泵血与血管阻力）"
    ],
    "confusion": "血压105/70是不是偏低了"
  },
  {
    "id": 56,
    "tags": [
      "血压形成原理（心脏泵血与血管阻力）",
      "长期高血压对血管壁损伤过程"
    ],
    "confusion": "血压130/80到底算不算高血压，需不需要干预"
  },
  {
    "id": 57,
    "tags": [
      "血压形成原理（心脏泵血与血管阻力）"
    ],
    "confusion": "血压130/85算不算高血压、中美标准为什么不同"
  },
  {
    "id": 58,
    "tags": [
      "血压形成原理（心脏泵血与血管阻力）",
      "长期高血压对血管壁损伤过程"
    ],
    "confusion": "血压135/85，没到140/90，需要吃降压药吗"
  },
  {
    "id": 59,
    "tags": [
      "血压形成原理（心脏泵血与血管阻力）",
      "低血压导致器官灌注不足示意"
    ],
    "confusion": "血压偏低对身体有没有坏处？"
  },
  {
    "id": 60,
    "tags": [
      "血压形成原理（心脏泵血与血管阻力）",
      "长期高血压对血管壁损伤过程"
    ],
    "confusion": "血压刚好140/90需不需要吃降压药"
  },
  {
    "id": 61,
    "tags": [
      "心力衰竭时心脏泵血功能下降示意",
      "低血压导致器官灌注不足示意"
    ],
    "confusion": "血压只有九十几一百是不是心衰、低血压危害大不大"
  },
  {
    "id": 62,
    "tags": [
      "血压测量时袖带压迫动脉原理示意"
    ],
    "confusion": "血压怎么测才准确"
  },
  {
    "id": 63,
    "tags": [
      "交感神经兴奋导致血管收缩与血压升高过程"
    ],
    "confusion": "血压总是控制不好，会不会和情绪有关？"
  },
  {
    "id": 64,
    "tags": [
      "血压形成原理（心脏泵血与血管阻力）",
      "长期高血压对血管壁损伤过程"
    ],
    "confusion": "血压控制到多少才是最理想的？"
  },
  {
    "id": 65,
    "tags": [
      "血压测量时袖带压迫动脉原理示意",
      "血压昼夜波动节律示意"
    ],
    "confusion": "血压每次测量结果差异大，是血压计不准还是自己的问题？"
  },
  {
    "id": 66,
    "tags": [
      "血压昼夜波动节律示意",
      "交感神经兴奋导致血管收缩与血压升高过程"
    ],
    "confusion": "血压波动大是什么原因"
  },
  {
    "id": 67,
    "tags": [
      "动脉硬化导致脉压差增大机制",
      "主动脉弹性减退示意"
    ],
    "confusion": "血压高压高低压低、压差大是病吗？怎么治？"
  },
  {
    "id": 68,
    "tags": [
      "骨髓中血小板生成与释放过程"
    ],
    "confusion": "血小板分布宽度升高是什么病"
  },
  {
    "id": 69,
    "tags": [
      "骨髓造血过程及各类血细胞分化示意"
    ],
    "confusion": "血常规化验单怎么看"
  },
  {
    "id": 70,
    "tags": [
      "骨髓造血过程及各类血细胞分化示意"
    ],
    "confusion": "血常规报告那么多箭头该怎么看，哪些指标最重要"
  },
  {
    "id": 71,
    "tags": [
      "动脉粥样硬化斑块破裂与血栓形成",
      "溶栓药物溶解血栓过程"
    ],
    "confusion": "血栓到底能不能被彻底清除？"
  },
  {
    "id": 72,
    "tags": [
      "血液流变学与红细胞聚集示意",
      "冠状动脉内斑块形成与狭窄进展过程"
    ],
    "confusion": "血液粘稠和心肌缺血是不是真正的医学概念"
  },
  {
    "id": 73,
    "tags": [
      "血液流变学与红细胞聚集示意"
    ],
    "confusion": "血液粘稠需要吃药或输液来降低吗？"
  },
  {
    "id": 74,
    "tags": [
      "血液流变学与红细胞聚集示意",
      "动脉粥样硬化斑块破裂与血栓形成"
    ],
    "confusion": "血液粘稠需要输液或吃保健品来预防心梗脑梗吗"
  },
  {
    "id": 75,
    "tags": [
      "冠状动脉微循环障碍示意",
      "冠状动脉痉挛过程"
    ],
    "confusion": "血管不堵为什么还会胸闷？"
  },
  {
    "id": 76,
    "tags": [
      "冠脉支架植入与血管扩张过程",
      "冠状动脉搭桥手术示意"
    ],
    "confusion": "血管严重狭窄但不想放支架，还能怎么办？"
  },
  {
    "id": 77,
    "tags": [
      "药物球囊扩张血管并释放药物过程",
      "冠脉支架植入与血管扩张过程"
    ],
    "confusion": "血管堵了可以不放支架用药物球囊吗？"
  },
  {
    "id": 78,
    "tags": [
      "冠脉支架植入与血管扩张过程",
      "冠状动脉搭桥手术示意"
    ],
    "confusion": "血管堵了放支架和做搭桥哪个更好？"
  },
  {
    "id": 79,
    "tags": [
      "冠状动脉内斑块形成与狭窄进展过程",
      "心肌缺血导致胸痛的传导通路"
    ],
    "confusion": "血管堵了身体会有什么感觉？"
  },
  {
    "id": 80,
    "tags": [
      "低密度脂蛋白在血管壁沉积过程",
      "冠状动脉内斑块形成与狭窄进展过程"
    ],
    "confusion": "血管堵塞/有斑块是因为吃肉太多吗？"
  },
  {
    "id": 81,
    "tags": [
      "低密度脂蛋白在血管壁沉积过程",
      "冠状动脉内斑块形成与狭窄进展过程"
    ],
    "confusion": "血管堵塞是不是因为肉吃多了？"
  },
  {
    "id": 82,
    "tags": [
      "低密度脂蛋白在血管壁沉积过程",
      "冠状动脉内斑块形成与狭窄进展过程"
    ],
    "confusion": "血管堵塞是因为吃肉太多吗？"
  },
  {
    "id": 83,
    "tags": [
      "冠状动脉侧支循环建立过程",
      "冠脉支架植入与血管扩张过程"
    ],
    "confusion": "血管堵死但有侧支循环，支架是不是白放了？"
  },
  {
    "id": 84,
    "tags": [
      "冠状动脉侧支循环建立过程",
      "冠状动脉慢性完全闭塞示意"
    ],
    "confusion": "血管完全堵死了为什么反而没症状？"
  },
  {
    "id": 85,
    "tags": [
      "冠状动脉内斑块形成与狭窄进展过程",
      "运动时冠状动脉血流变化示意"
    ],
    "confusion": "血管有斑块堵塞了还能不能运动、做什么运动好"
  },
  {
    "id": 86,
    "tags": [
      "冠状动脉内斑块形成与狭窄进展过程",
      "动脉粥样硬化斑块稳定化过程"
    ],
    "confusion": "血管有斑块应该怎么办？"
  },
  {
    "id": 87,
    "tags": [
      "冠状动脉内斑块形成与狭窄进展过程",
      "冠脉支架植入与血管扩张过程"
    ],
    "confusion": "血管狭窄90%但没有症状要不要放支架"
  },
  {
    "id": 88,
    "tags": [
      "冠状动脉内斑块形成与狭窄进展过程",
      "冠脉支架植入与血管扩张过程"
    ],
    "confusion": "血管狭窄到什么程度才需要放支架？"
  },
  {
    "id": 89,
    "tags": [
      "冠状动脉内斑块形成与狭窄进展过程",
      "冠脉支架植入与血管扩张过程",
      "药物球囊扩张血管并释放药物过程"
    ],
    "confusion": "血管狭窄到什么程度需要放支架、临界病变怎么选"
  },
  {
    "id": 90,
    "tags": [
      "血管钙化形成过程（钙盐在血管壁沉积）",
      "冠状动脉内斑块形成与狭窄进展过程"
    ],
    "confusion": "血管钙化还能不能吃钙片、如何预防血管钙化"
  },
  {
    "id": 91,
    "tags": [
      "胰岛β细胞分泌胰岛素过程",
      "血糖调节反馈机制示意"
    ],
    "confusion": "血糖轻微升高（糖尿病前期）需不需要吃药？"
  },
  {
    "id": 92,
    "tags": [
      "血糖调节反馈机制示意"
    ],
    "confusion": "血糖高是不是就不能吃水果了？"
  },
  {
    "id": 93,
    "tags": [
      "血浆置换/脂蛋白分离过程示意"
    ],
    "confusion": "血脂分离（洗血）真的能清除血管里的油脂吗"
  },
  {
    "id": 94,
    "tags": [
      "低密度脂蛋白在血管壁沉积过程",
      "他汀类药物抑制肝脏胆固醇合成机制"
    ],
    "confusion": "血脂到底多高需要吃药？为什么不同医生说法不一样？"
  },
  {
    "id": 95,
    "tags": [
      "脂蛋白颗粒（LDL、HDL、VLDL）结构与转运示意"
    ],
    "confusion": "血脂化验单应该怎么看？"
  },
  {
    "id": 96,
    "tags": [
      "他汀类药物抑制肝脏胆固醇合成机制",
      "低密度脂蛋白在血管壁沉积过程"
    ],
    "confusion": "血脂升高就一定要吃他汀吗"
  },
  {
    "id": 97,
    "tags": [
      "脂蛋白颗粒（LDL、HDL、VLDL）结构与转运示意"
    ],
    "confusion": "血脂报告那么多指标，到底该看哪个"
  },
  {
    "id": 98,
    "tags": [
      "低密度脂蛋白在血管壁沉积过程",
      "冠状动脉内斑块形成与狭窄进展过程"
    ],
    "confusion": "血脂高了很多年但没有斑块，是不是不用吃药？"
  },
  {
    "id": 99,
    "tags": [
      "无需动画"
    ],
    "confusion": "血脂高了饮食具体要注意什么"
  },
  {
    "id": 100,
    "tags": [
      "无需动画"
    ],
    "confusion": "血脂高应该怎么控制饮食？"
  },
  {
    "id": 101,
    "tags": [
      "肝脏胆固醇合成与脂蛋白代谢通路",
      "低密度脂蛋白在血管壁沉积过程"
    ],
    "confusion": "血脂高是什么原因导致的"
  },
  {
    "id": 102,
    "tags": [
      "无需动画"
    ],
    "confusion": "血脂高的人能不能喝全脂牛奶"
  },
  {
    "id": 103,
    "tags": [
      "肝脏胆固醇合成与脂蛋白代谢通路"
    ],
    "confusion": "血脂高的原因有哪些"
  },
  {
    "id": 104,
    "tags": [
      "动脉粥样硬化斑块破裂与血栓形成",
      "血液流变学与红细胞聚集示意"
    ],
    "confusion": "血黏度不高为什么还会心梗？"
  },
  {
    "id": 105,
    "tags": [
      "蜱虫叮咬传播病原体过程示意"
    ],
    "confusion": "被蜱虫咬了会感染什么病？大别班达病毒严不严重？"
  },
  {
    "id": 106,
    "tags": [
      "阿尔茨海默病脑内β-淀粉样蛋白沉积与神经元退化过程"
    ],
    "confusion": "记忆力下降是不是阿尔茨海默症？"
  },
  {
    "id": 107,
    "tags": [
      "动脉粥样硬化斑块破裂与血栓形成",
      "血栓脱落随血流栓塞远端血管过程"
    ],
    "confusion": "身体有血栓就容易心梗脑梗吗？"
  },
  {
    "id": 108,
    "tags": [
      "无需动画"
    ],
    "confusion": "轻断食（168断食法）会不会增加心血管病风险"
  },
  {
    "id": 109,
    "tags": [
      "冠状动脉内斑块形成与狭窄进展过程"
    ],
    "confusion": "输液能软化血管吗？"
  },
  {
    "id": 110,
    "tags": [
      "胰腺解剖结构与胰液分泌过程",
      "急性胰腺炎时胰酶自我消化过程"
    ],
    "confusion": "过年期间为什么胰腺炎高发？"
  },
  {
    "id": 111,
    "tags": [
      "无需动画"
    ],
    "confusion": "过度焦虑会影响治疗吗？"
  },
  {
    "id": 112,
    "tags": [
      "心脏电传导系统示意",
      "过量运动时心脏室颤发生过程"
    ],
    "confusion": "过量运动为什么会导致猝死"
  },
  {
    "id": 113,
    "tags": [
      "运动时血管壁剪切力变化示意",
      "冠状动脉内斑块形成与狭窄进展过程"
    ],
    "confusion": "过量运动真的会损害血管吗？"
  },
  {
    "id": 114,
    "tags": [
      "膝关节软骨退化与骨性关节炎进展过程",
      "关节软骨在适度运动中的营养代谢示意"
    ],
    "confusion": "运动会不会伤膝盖/导致膝关节炎？"
  },
  {
    "id": 115,
    "tags": [
      "无需动画"
    ],
    "confusion": "运动健身常见的误区有哪些？"
  },
  {
    "id": 116,
    "tags": [
      "心脏电传导系统示意",
      "过量运动时心脏室颤发生过程",
      "AED除颤恢复心律过程"
    ],
    "confusion": "运动员心脏骤停是怎么回事？能不能救回来？"
  },
  {
    "id": 117,
    "tags": [
      "运动时血管壁剪切力变化示意",
      "血压形成原理（心脏泵血与血管阻力）"
    ],
    "confusion": "运动时心率快血压高会不会损伤血管"
  },
  {
    "id": 118,
    "tags": [
      "无需动画"
    ],
    "confusion": "运动是出汗越多越好吗？"
  },
  {
    "id": 119,
    "tags": [
      "运动时血管壁剪切力变化示意"
    ],
    "confusion": "运动是否会直接损伤血管"
  },
  {
    "id": 120,
    "tags": [
      "酒精对心肌细胞损伤过程",
      "冠状动脉内斑块形成与狭窄进展过程"
    ],
    "confusion": "适量喝酒真的对心血管有益吗"
  },
  {
    "id": 121,
    "tags": [
      "冠状动脉造影检查过程示意",
      "冠状动脉内斑块形成与狭窄进展过程"
    ],
    "confusion": "通过血脂化验单算动脉硬化指数能否替代冠脉造影"
  },
  {
    "id": 122,
    "tags": [
      "肠道蠕动机制示意"
    ],
    "confusion": "长期便秘的原因是什么，怎么减少用药"
  },
  {
    "id": 123,
    "tags": [
      "他汀类药物抑制肝脏胆固醇合成机制",
      "血糖调节反馈机制示意"
    ],
    "confusion": "长期吃他汀会不会引起糖尿病"
  },
  {
    "id": 124,
    "tags": [
      "无需动画"
    ],
    "confusion": "长期吃药是不是要换着吃才能减少副作用"
  },
  {
    "id": 125,
    "tags": [
      "阿司匹林抑制血小板聚集机制",
      "脑出血时血肿压迫脑组织过程"
    ],
    "confusion": "长期吃阿司匹林会不会导致脑出血？"
  },
  {
    "id": 126,
    "tags": [
      "气道炎症反应与咳嗽反射弧示意"
    ],
    "confusion": "长期咳嗽一直不好是什么原因？"
  },
  {
    "id": 127,
    "tags": [
      "心力衰竭时肺淤血导致咳嗽机制",
      "气道炎症反应与咳嗽反射弧示意"
    ],
    "confusion": "长期咳嗽一直治不好，会不会是心脏问题（心衰）？"
  },
  {
    "id": 128,
    "tags": [
      "声波传入内耳与毛细胞损伤过程"
    ],
    "confusion": "长期戴耳机会不会损害听力"
  },
  {
    "id": 129,
    "tags": [
      "新冠病毒感染心肌细胞导致心肌炎过程",
      "心脏电传导系统示意"
    ],
    "confusion": "阳后心率变快心慌是不是心肌炎"
  },
  {
    "id": 130,
    "tags": [
      "新冠病毒感染心肌细胞导致心肌炎过程",
      "动脉粥样硬化斑块破裂与血栓形成"
    ],
    "confusion": "阳康后年轻人为什么容易心梗"
  },
  {
    "id": 131,
    "tags": [
      "阿司匹林抑制血小板聚集机制",
      "胃黏膜保护层被破坏导致溃疡过程"
    ],
    "confusion": "阿司匹林为什么容易引起出血？吃了之后身体发生了什么？"
  },
  {
    "id": 132,
    "tags": [
      "阿司匹林抑制血小板聚集机制",
      "胃黏膜保护层被破坏导致溃疡过程",
      "脑出血时血肿压迫脑组织过程"
    ],
    "confusion": "阿司匹林为什么既能防心梗又会引起胃溃疡和脑出血"
  },
  {
    "id": 133,
    "tags": [
      "阿司匹林抑制血小板聚集机制",
      "动脉粥样硬化斑块破裂与血栓形成"
    ],
    "confusion": "阿司匹林为什么能预防心梗？"
  },
  {
    "id": 134,
    "tags": [
      "阿司匹林抑制血小板聚集机制"
    ],
    "confusion": "阿司匹林哪些人该吃，怎么正确服用"
  },
  {
    "id": 135,
    "tags": [
      "阿司匹林抑制血小板聚集机制"
    ],
    "confusion": "阿司匹林应该什么时候吃、空腹还是餐后"
  },
  {
    "id": 136,
    "tags": [
      "阿司匹林抑制血小板聚集机制",
      "动脉粥样硬化斑块破裂与血栓形成"
    ],
    "confusion": "阿司匹林等常见药是不是该预防性吃？"
  },
  {
    "id": 137,
    "tags": [
      "阿司匹林抑制血小板聚集机制",
      "静脉血栓与动脉血栓形成机制对比"
    ],
    "confusion": "阿司匹林能防所有类型的血栓吗？"
  },
  {
    "id": 138,
    "tags": [
      "阿尔茨海默病脑内β-淀粉样蛋白沉积与神经元退化过程"
    ],
    "confusion": "阿尔茨海默病（老年痴呆）为什么容易被忽视"
  },
  {
    "id": 139,
    "tags": [
      "阿尔茨海默病脑内β-淀粉样蛋白沉积与神经元退化过程",
      "神经元突触传递功能退化示意"
    ],
    "confusion": "阿尔茨海默症是怎么回事"
  },
  {
    "id": 140,
    "tags": [
      "他汀类药物抑制肝脏胆固醇合成机制"
    ],
    "confusion": "阿托伐他汀必须晚上吃吗"
  },
  {
    "id": 141,
    "tags": [
      "无需动画"
    ],
    "confusion": "阿斯巴甜致癌吗，无糖饮料还能不能喝"
  },
  {
    "id": 142,
    "tags": [
      "无需动画"
    ],
    "confusion": "阿斯巴甜被列为致癌物，无糖饮料还能喝吗？"
  },
  {
    "id": 143,
    "tags": [
      "降压药作用于血管/心脏的机制示意",
      "肝脏胆固醇合成与脂蛋白代谢通路"
    ],
    "confusion": "降压药会不会升高血脂，高血脂的人能不能吃"
  },
  {
    "id": 144,
    "tags": [
      "降压药作用于血管/心脏的机制示意",
      "长期高血压对血管壁损伤过程"
    ],
    "confusion": "降压药吃上是不是就不能停了"
  },
  {
    "id": 145,
    "tags": [
      "肾上腺分泌醛固酮导致继发性高血压机制",
      "肾动脉狭窄导致高血压机制"
    ],
    "confusion": "降压药吃很多种血压还降不下来，会不会不是原发性高血压？"
  },
  {
    "id": 146,
    "tags": [
      "降压药作用于血管/心脏的机制示意"
    ],
    "confusion": "降压药怎么调整"
  },
  {
    "id": 147,
    "tags": [
      "降压药作用于血管/心脏的机制示意",
      "长期高血压对血管壁损伤过程"
    ],
    "confusion": "降压药是不是有依赖性，吃了就停不掉"
  },
  {
    "id": 148,
    "tags": [
      "无需动画"
    ],
    "confusion": "降压药是否致癌等常见健康谣言的真假"
  },
  {
    "id": 149,
    "tags": [
      "降压药作用于血管/心脏的机制示意"
    ],
    "confusion": "降压药漏吃了应该怎么补救？"
  },
  {
    "id": 150,
    "tags": [
      "降压药五大类作用靶点对比示意（ACEI、ARB、CCB、利尿剂、β受体阻滞剂）"
    ],
    "confusion": "降压药那么多种该怎么选？哪种效果最好？"
  },
  {
    "id": 1,
    "tags": [
      "尿酸代谢与肾脏排泄机制",
      "血脂在血管壁沉积过程"
    ],
    "confusion": "降尿酸药和降血脂药真的有用吗"
  },
  {
    "id": 2,
    "tags": [
      "降糖药肾脏代谢路径示意",
      "肾小球滤过机制"
    ],
    "confusion": "降糖药会不会伤肾"
  },
  {
    "id": 3,
    "tags": [
      "低密度脂蛋白在动脉壁沉积过程",
      "停药后斑块重新进展示意"
    ],
    "confusion": "降脂药为什么要长期坚持吃？"
  },
  {
    "id": 4,
    "tags": [
      "PCSK9抑制剂作用机制",
      "他汀类药物肝脏降脂机制"
    ],
    "confusion": "降脂针能不能代替他汀"
  },
  {
    "id": 5,
    "tags": [
      "无需动画"
    ],
    "confusion": "预算有限时体检应该优先查什么项目"
  },
  {
    "id": 6,
    "tags": [
      "动脉粥样硬化斑块破裂与血栓形成",
      "冠状动脉内斑块形成过程"
    ],
    "confusion": "预防心梗脑梗最重要的健康指标有哪些？"
  },
  {
    "id": 7,
    "tags": [
      "颈动脉低回声斑块超声影像示意",
      "斑块脱落引发脑梗塞过程"
    ],
    "confusion": "颈动脉低回声（软）斑块是不是很危险，会不会随时脑梗？"
  },
  {
    "id": 8,
    "tags": [
      "颈动脉易损斑块结构特征",
      "斑块脱落引发脑梗塞过程"
    ],
    "confusion": "颈动脉半年内突然长出易损斑块，会不会脑梗？"
  },
  {
    "id": 9,
    "tags": [
      "颈动脉与冠状动脉解剖位置对比",
      "冠状动脉内斑块形成过程"
    ],
    "confusion": "颈动脉彩超正常能说明心脏血管不堵吗"
  },
  {
    "id": 10,
    "tags": [
      "颈动脉支架植入手术过程",
      "颈动脉内膜剥脱术过程"
    ],
    "confusion": "颈动脉斑块为什么不直接取出来而是放支架"
  },
  {
    "id": 11,
    "tags": [
      "斑块脱落引发脑梗塞过程",
      "颈动脉斑块结构（纤维帽与脂质核心）"
    ],
    "confusion": "颈动脉斑块会不会脱落引起脑梗？"
  },
  {
    "id": 12,
    "tags": [
      "颈动脉内膜损伤与斑块形成过程",
      "低密度脂蛋白在动脉壁沉积过程"
    ],
    "confusion": "颈动脉斑块是怎么形成的"
  },
  {
    "id": 13,
    "tags": [
      "颈动脉内膜损伤与斑块形成过程",
      "动脉壁随年龄增厚退变过程"
    ],
    "confusion": "颈动脉斑块是疾病还是正常衰老"
  },
  {
    "id": 14,
    "tags": [
      "斑块稳定化与纤维帽增厚过程",
      "他汀类药物缩小斑块脂质核心示意"
    ],
    "confusion": "颈动脉斑块能不能缩小或消掉？"
  },
  {
    "id": 15,
    "tags": [
      "颈椎间盘突出压迫神经根示意",
      "颈椎退行性变结构变化"
    ],
    "confusion": "颈椎病怎么缓解，能治好吗"
  },
  {
    "id": 16,
    "tags": [
      "海姆立克急救法腹部冲击示意",
      "异物阻塞气道解剖示意"
    ],
    "confusion": "食物卡喉如何急救"
  },
  {
    "id": 17,
    "tags": [
      "无需动画"
    ],
    "confusion": "饭后哪些事能做哪些不能做"
  },
  {
    "id": 18,
    "tags": [
      "无需动画"
    ],
    "confusion": "饮食上怎么做能预防癌症"
  },
  {
    "id": 19,
    "tags": [
      "外源性与内源性血脂来源示意",
      "肝脏合成胆固醇与饮食胆固醇比例示意"
    ],
    "confusion": "饮食对血脂的影响到底有多大"
  },
  {
    "id": 20,
    "tags": [
      "肝脏内源性甘油三酯合成过程",
      "碳水化合物转化为甘油三酯路径"
    ],
    "confusion": "饮食已经很清淡了为什么甘油三酯还高？"
  },
  {
    "id": 21,
    "tags": [
      "肝脏内源性胆固醇合成过程",
      "外源性与内源性血脂来源示意"
    ],
    "confusion": "饮食已经很清淡了为什么血脂还是高"
  },
  {
    "id": 22,
    "tags": [
      "肝脏内源性胆固醇合成过程",
      "外源性与内源性血脂来源示意"
    ],
    "confusion": "饮食很清淡为什么血脂还是高？"
  },
  {
    "id": 23,
    "tags": [
      "外源性与内源性血脂来源示意",
      "肝脏合成胆固醇与饮食胆固醇比例示意"
    ],
    "confusion": "饮食控制对血脂的影响是不是只有20%、到底有没有用"
  },
  {
    "id": 24,
    "tags": [
      "骨质疏松骨小梁稀疏对比示意",
      "破骨细胞与成骨细胞骨重建平衡"
    ],
    "confusion": "骨质疏松是正常衰老还是需要重视的疾病？"
  },
  {
    "id": 25,
    "tags": [
      "高血压对血管壁持续损伤过程",
      "降压药作用机制示意"
    ],
    "confusion": "高血压一定要终身吃药吗"
  },
  {
    "id": 26,
    "tags": [
      "高血压发病机制（多因素）示意",
      "降压药作用机制示意"
    ],
    "confusion": "高血压为什么不能根治，是不是药企故意的"
  },
  {
    "id": 27,
    "tags": [
      "高血压导致肾小球损伤过程",
      "尿微量白蛋白检测原理示意"
    ],
    "confusion": "高血压为什么要验尿？"
  },
  {
    "id": 28,
    "tags": [
      "高血压导致肾小球损伤过程",
      "肾脏小动脉硬化过程"
    ],
    "confusion": "高血压会导致肾功能损害吗"
  },
  {
    "id": 29,
    "tags": [
      "继发性高血压病因筛查（肾上腺/肾动脉）",
      "多药联合降压作用靶点示意"
    ],
    "confusion": "高血压吃很多药还降不下来怎么办"
  },
  {
    "id": 30,
    "tags": [
      "无需动画"
    ],
    "confusion": "高血压患者到底应该怎么吃"
  },
  {
    "id": 31,
    "tags": [
      "高钠摄入导致血管内液量增加示意",
      "无需动画"
    ],
    "confusion": "高血压患者应该怎么吃？只少吃盐够不够？"
  },
  {
    "id": 32,
    "tags": [
      "高血压对血管壁持续损伤过程",
      "降压药作用机制示意"
    ],
    "confusion": "高血压是不是不该吃降压药？"
  },
  {
    "id": 33,
    "tags": [
      "高血压损害全身微循环示意",
      "高血压导致心脑肾眼靶器官损害"
    ],
    "confusion": "高血压是如何损害全身微循环和器官的"
  },
  {
    "id": 34,
    "tags": [
      "高血压发病机制（多因素）示意",
      "肾素-血管紧张素-醛固酮系统调节示意"
    ],
    "confusion": "高血压是怎么形成的？"
  },
  {
    "id": 35,
    "tags": [
      "高血压发病机制（多因素）示意",
      "降压药作用机制示意"
    ],
    "confusion": "高血压有没有可能根治"
  },
  {
    "id": 36,
    "tags": [
      "高血压发病机制（多因素）示意"
    ],
    "confusion": "高血压根治话术为什么是骗人的"
  },
  {
    "id": 37,
    "tags": [
      "降压药维持血药浓度曲线示意",
      "停药后血管阻力回升过程"
    ],
    "confusion": "高血压的药为什么一停血压就升高"
  },
  {
    "id": 38,
    "tags": [
      "高血压对血管壁持续损伤过程",
      "降压药维持血药浓度曲线示意"
    ],
    "confusion": "高血压能不能停药，必须吃一辈子吗"
  },
  {
    "id": 39,
    "tags": [
      "高血压发病机制（多因素）示意"
    ],
    "confusion": "高血压能不能根治（识别骗局）"
  },
  {
    "id": 40,
    "tags": [
      "高血压发病机制（多因素）示意",
      "降压药作用机制示意"
    ],
    "confusion": "高血压能不能逆转，是否必须终生服药"
  },
  {
    "id": 41,
    "tags": [
      "血压水平与心脑血管风险关系曲线",
      "高血压损害全身微循环示意"
    ],
    "confusion": "高血压诊断标准为什么从140/90降到130/80？"
  },
  {
    "id": 42,
    "tags": [
      "血压水平与心脑血管风险关系曲线"
    ],
    "confusion": "高血压诊断标准到底是140/90还是130/80"
  },
  {
    "id": 43,
    "tags": [
      "家族性高胆固醇血症基因遗传示意",
      "LDL受体基因突变导致血脂升高机制"
    ],
    "confusion": "高血脂会遗传吗？父母血脂高自己一定也会高吗？"
  },
  {
    "id": 44,
    "tags": [
      "肝脏合成与代谢血脂过程",
      "脂肪肝与血脂异常关系示意"
    ],
    "confusion": "高血脂和肝脏有什么关系？"
  },
  {
    "id": 45,
    "tags": [
      "无需动画"
    ],
    "confusion": "高血脂应该怎么吃"
  },
  {
    "id": 46,
    "tags": [
      "外源性与内源性血脂来源示意",
      "肝脏内源性胆固醇合成过程"
    ],
    "confusion": "高血脂是不是吃肉吃出来的"
  },
  {
    "id": 47,
    "tags": [
      "Omega-3脂肪酸抗炎与降甘油三酯机制"
    ],
    "confusion": "鱼油到底能不能吃，有没有必要补充"
  },
  {
    "id": 48,
    "tags": [
      "膳食胆固醇消化吸收与肝脏代谢路径",
      "肝脏合成胆固醇与饮食胆固醇比例示意"
    ],
    "confusion": "鸡蛋每天吃几个合适？血脂高能不能吃蛋黄？"
  },
  {
    "id": 49,
    "tags": [
      "鼻腔黏膜充血肿胀与鼻甲结构示意"
    ],
    "confusion": "鼻塞有什么有效的缓解方法？"
  }
]